Workbook
Name Absa__GH__LTD: 'Bank Data'!$C$3:$C$97
Name Access_Bank__Ghana__Plc: 'Bank Data'!$F$3:$F$55
Name Agricultural_Development_Bank_Limited: 'Bank Data'!$I$3:$I$94
Name Apex_Bank_GH_Limited: 'Bank Data'!$L$3:$L$164
Name Bank_of_Africa_Ghana_Limited: 'Bank Data'!$O$3:$O$31
Name Bank_of_Ghana: 'Bank Data'!$R$3:$R$12
Name BankBranchCode: 'Bank Data'!$CI$3:$CI$1508
Name BankBranchName: 'Bank Data'!$CH$3:$CH$1508
Name BankName: 'Bank Data'!$A$3:$A$30
Name BSIC_Ghana_Limited: 'Bank Data'!$U$3:$U$16
Name CAL_Bank_Limited: 'Bank Data'!$X$3:$X$42
Name Consolidated_Bank_Ghana_Limited: 'Bank Data'!$AA$3:$AA$119
Name Ecobank_Ghana_Limited: 'Bank Data'!$AD$3:$AD$91
Name FBN_Bank__Ghana__Limited: 'Bank Data'!$AG$3:$AG$22
Name Fidelity_Bank_Limited: 'Bank Data'!$AJ$3:$AJ$94
Name First_Atlantic_Bank_Limited: 'Bank Data'!$AM$3:$AM$38
Name First_National_Bank__Ghana__Limited: 'Bank Data'!$AP$3:$AP$11
Name GCB_Bank_Limited: 'Bank Data'!$AS$3:$AS$194
Name GHL_Bank_Limited: 'Bank Data'!$AV$3:$AV$6
Name GN_Bank_Limited: 'Bank Data'!#REF!
Name Guaranty_Trust_Bank__Ghana__Limited: 'Bank Data'!$AZ$3:$AZ$43
Name National_Investment_Bank_Limited: 'Bank Data'!$BC$3:$BC$70
Name Omni_Bank_Ghana_Limited: 'Bank Data'!$BF$3:$BF$28
Name Prudential_Bank_Limited: 'Bank Data'!$BI$3:$BI$43
Name Republic_Bank__Ghana__Limited: 'Bank Data'!$BL$3:$BL$50
Name Societe_General__Ghana__Limited: 'Bank Data'!$BO$3:$BO$52
Name Stanbic_Bank_Ghana_Limited: 'Bank Data'!$BR$3:$BR$49
Name Standard_Chartered_Bank__Ghana__Limited: 'Bank Data'!$BU$3:$BU$25
Name United_Bank_for_Africa__Ghana__Limited: 'Bank Data'!$BX$3:$BX$25
Name Universal_Merchant_Bank_Limited: 'Bank Data'!$CA$3:$CA$59
Name Zenith_Bank__Ghana__Limited: 'Bank Data'!$CD$3:$CD$30

Sheet employees
A1: Required Information | G1: Additional Information (Optional) | R1: Other Information
A2: FirstName | B2: LastName | C2: BasicSalary | D2: SocialSecurityNumber | E2: EmailAddress | F2: MobileNumber | G2: OtherNames | H2: EmployeeTrusteeId | I2: WorkerType | J2: PaymentDestination | K2: BankName | L2: BankBranchName | M2: BankBranchSortCode | N2: BankAccountName | O2: BankAccountNumber | P2: MomoNetwork | Q2: MomoAccountName | R2: MomoAccountNumber | S2: Gender | T2: MaritalStatus | U2: BirthDate | V2: Nationality | W2: NationalIdType | X2: NationalIdNumber | Y2: EmployeeNumber | Z2: EmployeeStatus | AA2: EmployeeStatusEndDate | AB2: HireDate | AC2: JobPosition | AD2: Department | AE2: Division | AF2: Unit | AG2: PayBand | AH2: Location | AI2: IncludeInPayroll | AJ2: PayType | AK2: Currency
A3: PEARL | B3: WEBU | C3: 3391.54 | D3: C19304210265 | E3: webupearl392@gmail.com | F3: 0544628316 | I3: EMPLOYEE | M3: =_xlfn.IFNA(VLOOKUP(_xlfn.CONCAT(K3,L3),'Bank Data'!$CH$3:$CI$1508,2,0),"") | S3: FEMALE | T3: MARRIED | V3: Ghana | W3: GHANA CARD | X3: GHA-712506684-9 | Y3: NKA209 | AB3: 01/11/2021 | AC3: CHECK IN OFFICER | AF3: AIRPORT | AH3: AIRPORT | AI3: YES | AJ3: SALARY | AK3: GHS
A4: GLORIA | B4: SEFAH SAAH | C4: 5239.05 | D4: J018110290025 | E4: kespong20156@gmail.com | F4: 0202735517 | I4: EMPLOYEE | M4: =_xlfn.IFNA(VLOOKUP(_xlfn.CONCAT(K4,L4),'Bank Data'!$CH$3:$CI$1508,2,0),"") | S4: FEMALE | T4: MARRIED | V4: Ghana | W4: GHANA CARD | X4: GHA-001364952-8 | Y4: NKA060 | AB4: 01/08/2007 | AC4: IMAGE ANALYST | AF4: AIRPORT | AH4: AIRPORT | AI4: YES | AJ4: SALARY | AK4: GHS
A5: KOFI | B5: NANA ADJEI | C5: 6715.48 | E5: nanakofiadjei1929@gmail.com | F5: 0505718804 | I5: EMPLOYEE | M5: =_xlfn.IFNA(VLOOKUP(_xlfn.CONCAT(K5,L5),'Bank Data'!$CH$3:$CI$1508,2,0),"") | S5: MALE | V5: Ghana | W5: GHANA CARD | X5: GHA-725971370-7 | Y5: NTE140 | AB5: 04/08/2015 | AC5: COODINATOR | AF5: TEMA MAIN | AH5: TEMA MAIN | AI5: YES | AJ5: SALARY | AK5: GHS
A6: OSMAN | B6: AWE ADDA | C6: 1463.09 | D6: J138001010039 | E6: aweoman8002@gmail.com | F6: 0543816312 | I6: EMPLOYEE | M6: =_xlfn.IFNA(VLOOKUP(_xlfn.CONCAT(K6,L6),'Bank Data'!$CH$3:$CI$1508,2,0),"") | S6: MALE | V6: Ghana | W6: GHANA CARD | X6: GHA-727455931-3 | Y6: NPA224 | AB6: 01/11/2021 | AC6: SECURITY | AF6: PAGA | AH6: PAGA | AI6: YES | AJ6: SALARY | AK6: GHS
A7: ALICE | B7: BAFFOE | C7: 3594.51 | D7: G097911120020 | E7: obaapayiwa@yahoo.com | F7: 0245697254 | I7: EMPLOYEE | M7: =_xlfn.IFNA(VLOOKUP(_xlfn.CONCAT(K7,L7),'Bank Data'!$CH$3:$CI$1508,2,0),"") | S7: FEMALE | V7: Ghana | W7: GHANA CARD | X7: GHA-713421810-1 | Y7: NKA118 | AB7: 02/01/2014 | AC7: CHECK IN OFFICER | AF7: AIRPORT | AH7: AIRPORT | AI7: YES | AJ7: SALARY | AK7: GHS
A8: AUGUSTINE | B8: EFFAH | C8: 3438.85 | D8: G098502250019 | E8: augustineeffah5@gmail.com | F8: 0242226571 | I8: EMPLOYEE | M8: =_xlfn.IFNA(VLOOKUP(_xlfn.CONCAT(K8,L8),'Bank Data'!$CH$3:$CI$1508,2,0),"") | S8: MALE | T8: MARRIED | V8: Ghana | W8: GHANA CARD | X8: GHA-001100473-2 | Y8: NTE156 | AB8: 01/02/2016 | AC8: DRIVER | AF8: TEMA MAIN | AH8: TEMA MAIN | AI8: YES | AJ8: SALARY | AK8: GHS
A9: JOANA | B9: BOAMPONG | C9: 4653 | D9: E018612210025 | E9: joanaboampong@yahoo.com | F9: 0246412874 | I9: EMPLOYEE | M9: =_xlfn.IFNA(VLOOKUP(_xlfn.CONCAT(K9,L9),'Bank Data'!$CH$3:$CI$1508,2,0),"") | S9: FEMALE | V9: Ghana | W9: GHANA CARD | X9: GHA-001282314-5 | Y9: NKA093 | AB9: 04/03/2013 | AC9: IMAGE ANALYST | AF9: AIRPORT | AH9: AIRPORT | AI9: YES | AJ9: SALARY | AK9: GHS
A10: JOY | B10: KAFUI KWAKUYI | C10: 3716.51 | D10: C019201140375 | E10: joy.kafui@yahoo.com | F10: 0269408482 | I10: EMPLOYEE | M10: =_xlfn.IFNA(VLOOKUP(_xlfn.CONCAT(K10,L10),'Bank Data'!$CH$3:$CI$1508,2,0),"") | S10: MALE | V10: Ghana | W10: GHANA CARD | X10: GHA-002422937-3 | Y10: NPA192 | AB10: 01/01/2018 | AC10: IMAGE ANALYST | AF10: PAGE | AH10: PAGE | AI10: YES | AJ10: SALARY | AK10: GHS
A11: BRIGHT | B11: MENKA ASARE | C11: 16546.48 | D11: G097806130011 | E11: bmasare@gmail.com | F11: 0244096691 | I11: EMPLOYEE | M11: =_xlfn.IFNA(VLOOKUP(_xlfn.CONCAT(K11,L11),'Bank Data'!$CH$3:$CI$1508,2,0),"") | S11: MALE | T11: MARRIED | V11: Ghana | W11: GHANA CARD | X11: GHA-713483593-1 | Y11: NTE008 | AB11: 01/03/2004 | AC11: MANAGER -TEMA | AF11: TEMA MAIN | AH11: TEMA MAIN | AI11: YES | AJ11: SALARY | AK11: GHS
A12: SADAT | B12: ADAM SINARE | C12: 9880.88 | D12: C018512190115 | E12: sinare19@yahoo.com | F12: 0244669561 | I12: EMPLOYEE | M12: =_xlfn.IFNA(VLOOKUP(_xlfn.CONCAT(K12,L12),'Bank Data'!$CH$3:$CI$1508,2,0),"") | S12: MALE | T12: MARRIED | V12: Ghana | W12: GHANA CARD | X12: GHA-727378066-4 | Y12: NTE012 | AB12: 01/08/2011 | AC12: ASSISTANT MANAGER SENTRY PORTAL | AF12: TEMA-SENTRY PORTAL | AH12: TEMA-SENTRY PORTAL | AI12: YES | AJ12: SALARY | AK12: GHS
A13: ALBERT | B13: SOWA BOYE | C13: 3350.51 | D13: C017208240479 | E13: bertocalus@gmail.com | F13: 0244816212 | I13: EMPLOYEE | M13: =_xlfn.IFNA(VLOOKUP(_xlfn.CONCAT(K13,L13),'Bank Data'!$CH$3:$CI$1508,2,0),"") | S13: MALE | T13: MARRIED | V13: Ghana | W13: GHANA CARD | X13: GHA-003697605-2 | Y13: NPA193 | AB13: 01/01/2018 | AC13: I.T OFFICER | AF13: PAGA | AH13: PAGA | AI13: YES | AJ13: SALARY | AK13: GHS
A14: PRINCE | B14: MARMAH | C14: 6882.35 | D14: F019004240053 | E14: marmahp@gmail.com | F14: 0242373473 | I14: EMPLOYEE | M14: =_xlfn.IFNA(VLOOKUP(_xlfn.CONCAT(K14,L14),'Bank Data'!$CH$3:$CI$1508,2,0),"") | S14: MALE | T14: MARRIED | V14: Ghana | W14: GHANA CARD | X14: GHA-727288015-0 | Y14: NKA112 | AB14: 02/09/2013 | AC14: ASSISTANT INFO TECH MANAGER | AF14: TEMA MAIN | AH14: TEMA MAIN | AI14: YES | AJ14: SALARY | AK14: GHS
A15: KINGFUL | B15: ACQUAH KOBINA | C15: 9696.55 | D15: B116709280059 | E15: kingfula@yahoo.com | F15: 0244624471 | I15: EMPLOYEE | M15: =_xlfn.IFNA(VLOOKUP(_xlfn.CONCAT(K15,L15),'Bank Data'!$CH$3:$CI$1508,2,0),"") | S15: MALE | T15: MARRIED | V15: Ghana | W15: GHANA CARD | X15: GHA-728079380-8 | Y15: NAF043 | AB15: 01/05/2015 | AC15: IMAGE AUDITOR | AF15: ICUMS | AH15: ICUMS | AI15: YES | AJ15: SALARY | AK15: GHS
A16: AKUA | B16: NANA FOSUA | C16: 1737.57 | E16: nanakadira54@gmail.com | F16: 0540988361 | I16: EMPLOYEE | M16: =_xlfn.IFNA(VLOOKUP(_xlfn.CONCAT(K16,L16),'Bank Data'!$CH$3:$CI$1508,2,0),"") | S16: FEMALE | V16: Ghana | W16: GHANA CARD | X16: GHA-724982985-2 | Y16: NAF214 | AB16: 01/11/2021 | AC16: OFFICE ASSISTANT | AF16: AFLAO | AH16: AFLAO | AI16: YES | AJ16: SALARY | AK16: GHS
A17: AMARTEY | B17: SOTTI | C17: 3161.91 | D17: D077605050130 | E17: tottieamartey@gmail.com | F17: 0206848005 | I17: EMPLOYEE | M17: =_xlfn.IFNA(VLOOKUP(_xlfn.CONCAT(K17,L17),'Bank Data'!$CH$3:$CI$1508,2,0),"") | S17: MALE | T17: SINGLE | V17: Ghana | W17: GHANA CARD | X17: GHA-728750571-6 | Y17: NKA110 | AB17: 01/02/2016 | AC17: DRIVER | AF17: TEMA | AH17: TEMA | AI17: YES | AJ17: SALARY | AK17: GHS
A18: ASMAWU | B18: MOHAMMED | C18: 4359 | D18: C018704130521 | E18: schimelda30@gmail.com | F18: 0243335576 | I18: EMPLOYEE | M18: =_xlfn.IFNA(VLOOKUP(_xlfn.CONCAT(K18,L18),'Bank Data'!$CH$3:$CI$1508,2,0),"") | S18: FEMALE | T18: MARRIED | V18: Ghana | W18: GHANA CARD | X18: GHA-002515850-6 | Y18: NKA137 | AB18: 01/02/2015 | AC18: IMAGE ANALYST | AF18: AIRPORT | AH18: AIRPORT | AI18: YES | AJ18: SALARY | AK18: GHS
A19: KWADWO | B19: AMISSAH OPOKU | C19: 7076 | D19: C017006240155 | I19: EMPLOYEE | M19: =_xlfn.IFNA(VLOOKUP(_xlfn.CONCAT(K19,L19),'Bank Data'!$CH$3:$CI$1508,2,0),"") | S19: MALE | V19: Ghana | W19: GHANA CARD | X19: GHA-001067885-1 | Y19: NTE185 | AB19: 01/02/2015 | AC19: SUPERVISOR | AF19: GHANA LINK | AH19: GHANA LINK | AI19: YES | AJ19: SALARY | AK19: GHS
A20: PONTIAC | B20: AYI | C20: 3771.91 | D20: G097908010056 | E20: akwakupontiac@gmail.com | I20: EMPLOYEE | M20: =_xlfn.IFNA(VLOOKUP(_xlfn.CONCAT(K20,L20),'Bank Data'!$CH$3:$CI$1508,2,0),"") | S20: MALE | V20: Ghana | W20: GHANA CARD | X20: GHA-713594758-0 | Y20: NAF048 | AB20: 01/11/2011 | AC20: TRAFFIC MARSHAL | AF20: AFLAO | AH20: AFLAO | AI20: YES | AJ20: SALARY | AK20: GHS
A21: GYASI | B21: ACHEAMPONG | C21: 2940.59 | D21: G099306020013 | E21: acheamponggyasi@gmail.com | F21: 0548068581 | I21: EMPLOYEE | M21: =_xlfn.IFNA(VLOOKUP(_xlfn.CONCAT(K21,L21),'Bank Data'!$CH$3:$CI$1508,2,0),"") | S21: MALE | V21: Ghana | W21: GHANA CARD | X21: GHA-715548139-3 | Y21: NKA229 | AC21: CHECK IN OFFICER | AF21: AIRPORT | AH21: AIRPORT | AI21: YES | AJ21: SALARY | AK21: GHS
A22: EMMA | B22: BAAH | C22: 4409.45 | D22: C017804210202 | E22: baahe067@gmail.com | F22: 0262685590 | I22: EMPLOYEE | M22: =_xlfn.IFNA(VLOOKUP(_xlfn.CONCAT(K22,L22),'Bank Data'!$CH$3:$CI$1508,2,0),"") | S22: FEMALE | V22: Ghana | W22: GHANA CARD | X22: GHA-000422388-3 | Y22: NTE174 | AB22: 01/11/2016 | AC22: CHECK IN OFFICER | AF22: AIRPORT | AH22: AIRPORT | AI22: YES | AJ22: SALARY | AK22: GHS
A23: ROSENKLE | B23: P. OFORI | C23: 5690.45 | D23: G097911110013 | E23: sosspanin@gmail.com | F23: 0244129875 | I23: EMPLOYEE | M23: =_xlfn.IFNA(VLOOKUP(_xlfn.CONCAT(K23,L23),'Bank Data'!$CH$3:$CI$1508,2,0),"") | S23: MALE | T23: MARRIED | V23: Ghana | W23: GHANA CARD | X23: GHA-720253575-4 | Y23: NTA029 | AB23: 02/02/2009 | AC23: IMAGE ANALYST | AF23: TAKORADI | AH23: TAKORADI | AI23: YES | AJ23: SALARY | AK23: GHS
A24: KWESI | B24: AFFUL MORRISON | C24: 3727.99 | D24: C107511160017 | F24: 0203494743 | I24: EMPLOYEE | M24: =_xlfn.IFNA(VLOOKUP(_xlfn.CONCAT(K24,L24),'Bank Data'!$CH$3:$CI$1508,2,0),"") | S24: MALE | T24: MARRIED | V24: Ghana | W24: GHANA CARD | X24: GHA-712126870-6 | Y24: NKA068 | AB24: 01/11/2011 | AC24: TRAFFIC MARSHAL | AF24: TEMA - SENTRY PORTAL | AH24: TEMA - SENTRY PORTAL | AI24: YES | AJ24: SALARY | AK24: GHS
A25: ANN | B25: BAFFOE | C25: 3391.54 | D25: G099810300024 | E25: baffoaann11@gmail.com | F25: 0507909742 | I25: EMPLOYEE | M25: =_xlfn.IFNA(VLOOKUP(_xlfn.CONCAT(K25,L25),'Bank Data'!$CH$3:$CI$1508,2,0),"") | S25: FEMALE | T25: SINGLE | V25: Ghana | W25: GHANA CARD | X25: GHA-726379417-8 | Y25: NTE208 | AB25: 01/11/2021 | AC25: SECRETARY | AF25: TEMA MAIN | AH25: TEMA MAIN | AI25: YES | AJ25: SALARY | AK25: GHS
A26: JOSEPH | B26: ATINGA APERIKA | C26: 1463.09 | D26: J019212220014 | E26: atingajoseph22@gmail.com | F26: 0549566865 | I26: EMPLOYEE | M26: =_xlfn.IFNA(VLOOKUP(_xlfn.CONCAT(K26,L26),'Bank Data'!$CH$3:$CI$1508,2,0),"") | S26: MALE | V26: Ghana | W26: GHANA CARD | X26: GHA-723286647-3 | Y26: NPA225 | AB26: 01/11/2021 | AC26: SECURITY | AF26: PAGA | AH26: PAGA | AI26: YES | AJ26: SALARY | AK26: GHS
A27: EMMANUEL | B27: EDEM NUKU | C27: 2984.51 | D27: R369705240013 | E27: edemnuku@gmail.com | F27: 0556283143 | I27: EMPLOYEE | M27: =_xlfn.IFNA(VLOOKUP(_xlfn.CONCAT(K27,L27),'Bank Data'!$CH$3:$CI$1508,2,0),"") | S27: MALE | V27: Ghana | W27: GHANA CARD | X27: GHA-727301828-2 | Y27: NKA160 | AB27: 04/07/2016 | AC27: CHECK IN OFFICER | AF27: AIRPORT | AH27: AIRPORT | AI27: YES | AJ27: SALARY | AK27: GHS
A28: SANI | B28: ALIDU AHMED | C28: 4658.4 | D28: C037106210039 | E28: ahsani.alidu@gmail.com | F28: 0240000016 | I28: EMPLOYEE | M28: =_xlfn.IFNA(VLOOKUP(_xlfn.CONCAT(K28,L28),'Bank Data'!$CH$3:$CI$1508,2,0),"") | S28: MALE | T28: MARRIED | V28: Ghana | W28: GHANA CARD | X28: GHA-001427133-9 | Y28: NTE194 | AC28: DRIVER | AF28: GHANA LINK | AH28: GHANA LINK | AI28: YES | AJ28: SALARY | AK28: GHS
A29: COLLINS | B29: OPOKU SEFAH | C29: 3527.91 | D29: G098407180016 | E29: collinsopoku135@gmail.com | F29: 0203278103 | I29: EMPLOYEE | M29: =_xlfn.IFNA(VLOOKUP(_xlfn.CONCAT(K29,L29),'Bank Data'!$CH$3:$CI$1508,2,0),"") | S29: MALE | V29: Ghana | W29: GHANA CARD | X29: GHA-726679782-8 | Y29: NTE104 | AB29: 04/03/2013 | AC29: TRAFFIC MARSHAL | AF29: TEMA - SENTRY PORTAL | AH29: TEMA - SENTRY PORTAL | AI29: YES | AJ29: SALARY | AK29: GHS
A30: RICHARD | B30: KROBILA | C30: 3217.51 | D30: C109007230172 | E30: rkrodilla@yahoo.com | F30: 0540867305 | I30: EMPLOYEE | M30: =_xlfn.IFNA(VLOOKUP(_xlfn.CONCAT(K30,L30),'Bank Data'!$CH$3:$CI$1508,2,0),"") | S30: MALE | T30: SINGLE | V30: Ghana | W30: GHANA CARD | X30: GHA-000986884-9 | Y30: NTAT01 | AB30: 01/09/2017 | AC30: IMAGE ANALYST | AF30: TEMA-SENTRY PORTAL | AH30: TEMA-SENTRY PORTAL | AI30: YES | AJ30: SALARY | AK30: GHS
A31: CECILIA | B31: KYEREWAA DANSO | C31: 4359 | D31: R368007220046 | E31: ceciliakyerewaa123@gmail.com | F31: 0241191657 | I31: EMPLOYEE | M31: =_xlfn.IFNA(VLOOKUP(_xlfn.CONCAT(K31,L31),'Bank Data'!$CH$3:$CI$1508,2,0),"") | S31: FEMALE | T31: MARRIED | V31: Ghana | W31: GHANA CARD | X31: GHA-001728672-7 | Y31: NTE027 | AB31: 29/09/2005 | AC31: OFFICE ASSISTANT | AF31: AIRPORT | AH31: AIRPORT | AI31: YES | AJ31: SALARY | AK31: GHS
A32: KWABENA | B32: GYASI | C32: 9093.81 | D32: F177909110058 | E32: kygyasi31@gmail.com | F32: 0244840874 | I32: EMPLOYEE | M32: =_xlfn.IFNA(VLOOKUP(_xlfn.CONCAT(K32,L32),'Bank Data'!$CH$3:$CI$1508,2,0),"") | S32: MALE | T32: MARRIED | V32: Ghana | W32: GHANA CARD | X32: GHA-002405291-5 | Y32: NTE014 | AB32: 01/10/2004 | AC32: ASSISTANT MANAGER AIRPORT | AF32: AIRPORT | AH32: AIRPORT | AI32: YES | AJ32: SALARY | AK32: GHS
A33: MARK | B33: KOFI ADADE NYASUNU | C33: 3405.91 | D33: A167302020012 | E33: marknyaseinu@gmail.com | F33: 0240505825 | I33: EMPLOYEE | M33: =_xlfn.IFNA(VLOOKUP(_xlfn.CONCAT(K33,L33),'Bank Data'!$CH$3:$CI$1508,2,0),"") | S33: MALE | T33: MARRIED | V33: Ghana | W33: GHANA CARD | X33: GHA-713689862-8 | Y33: NKA075 | AB33: 01/06/2012 | AC33: CLEANER/OFFICE ASSISTANT | AF33: AFLAO | AH33: AFLAO | AI33: YES | AJ33: SALARY | AK33: GHS
A34: PAA | B34: KWESI AHINKURAH | C34: 4154.87 | D34: C016508310058 | E34: pahinkurah@yahoo.com | F34: 0275452291 | I34: EMPLOYEE | M34: =_xlfn.IFNA(VLOOKUP(_xlfn.CONCAT(K34,L34),'Bank Data'!$CH$3:$CI$1508,2,0),"") | S34: MALE | T34: MARRIED | V34: Ghana | W34: GHANA CARD | X34: GHA-720215683-4 | Y34: NTA034 | AB34: 01/08/2007 | AC34: IMAGE ANALYST | AF34: TAKORADI | AH34: TAKORADI | AI34: YES | AJ34: SALARY | AK34: GHS
A35: KWAME | B35: FRIMPONG NTIAMOAH | C35: 1463.09 | D35: F069209190011 | E35: nanakwamefrimpong092@gmail.com | F35: 0248249033 | I35: EMPLOYEE | M35: =_xlfn.IFNA(VLOOKUP(_xlfn.CONCAT(K35,L35),'Bank Data'!$CH$3:$CI$1508,2,0),"") | S35: MALE | V35: Ghana | W35: GHANA CARD | X35: GHA-715335657-8 | Y35: NPA220 | AB35: 01/11/2021 | AC35: TRAFFIC MARSHAL | AF35: PAGE | AH35: PAGE | AI35: YES | AJ35: SALARY | AK35: GHS
A36: SIMON | B36: ASARE STONE | C36: 3527.91 | D36: G018610290117 | E36: de.stone2021@gmail.com | F36: 0243111658 | I36: EMPLOYEE | M36: =_xlfn.IFNA(VLOOKUP(_xlfn.CONCAT(K36,L36),'Bank Data'!$CH$3:$CI$1508,2,0),"") | S36: MALE | T36: MARRIED | V36: Ghana | W36: GHANA CARD | X36: GHA-713582875-8 | Y36: NAF153 | AB36: 01/02/2016 | AC36: IMAGE ANALYST | AF36: AFLAO | AH36: AFLAO | AI36: YES | AJ36: SALARY | AK36: GHS
A37: BRIGHT | B37: ADU AGYAPONG | C37: 4897.45 | D37: F018506060359 | E37: rockyjbright@yahoo.com | F37: 0243236552 | I37: EMPLOYEE | M37: =_xlfn.IFNA(VLOOKUP(_xlfn.CONCAT(K37,L37),'Bank Data'!$CH$3:$CI$1508,2,0),"") | S37: MALE | T37: MARRIED | V37: Ghana | W37: GHANA CARD | X37: GHA-729090384-2 | Y37: NTE080 | AB37: 01/06/2012 | AC37: CHECK IN OFFICER | AF37: AIRPORT | AH37: AIRPORT | AI37: YES | AJ37: SALARY | AK37: GHS
A38: AUGUSTINE | B38: OSEI | C38: 3039.91 | D38: G018505290075 | E38: augustuneosei40@gmail.com | F38: 0248611018 | I38: EMPLOYEE | M38: =_xlfn.IFNA(VLOOKUP(_xlfn.CONCAT(K38,L38),'Bank Data'!$CH$3:$CI$1508,2,0),"") | S38: MALE | V38: Ghana | W38: GHANA CARD | X38: GHA-712158808-2 | Y38: NKA139 | AB38: 02/01/2014 | AC38: TRAFFIC MARSHAL | AF38: AIRPORT | AH38: AIRPORT | AI38: YES | AJ38: SALARY | AK38: GHS
A39: SAMUEL | B39: ANTWI | C39: 1480.61 | D39: G099305250070 | E39: samuelantwikwadwo@gmail.com | F39: 0551826186 | I39: EMPLOYEE | M39: =_xlfn.IFNA(VLOOKUP(_xlfn.CONCAT(K39,L39),'Bank Data'!$CH$3:$CI$1508,2,0),"") | S39: MALE | V39: Ghana | W39: GHANA CARD | X39: GHA-725457015-2 | Y39: NTE218 | AB39: 01/11/2021 | AC39: TRAFFIC MARSHAL | AF39: TEMA - SENTRY PORTAL | AH39: TEMA - SENTRY PORTAL | AI39: YES | AJ39: SALARY | AK39: GHS
A40: GENEVIEVE | B40: ADDY | C40: 5189.05 | D40: C038403210084 | E40: Naa18addy@yahoo.com | F40: 0244845465 | I40: EMPLOYEE | M40: =_xlfn.IFNA(VLOOKUP(_xlfn.CONCAT(K40,L40),'Bank Data'!$CH$3:$CI$1508,2,0),"") | S40: FEMALE | T40: MARRIED | V40: Ghana | W40: GHANA CARD | X40: GHA-000224347-0 | Y40: NKA132 | AB40: 02/04/2014 | AC40: SECRETARY | AF40: AIRPORT | AH40: AIRPORT | AI40: YES | AJ40: SALARY | AK40: GHS
A41: MONICA | B41: PAINTSIL | C41: 5189.05 | D41: C018806080169 | E41: lasmonic@yahoo.com | F41: 0245515141 | I41: EMPLOYEE | M41: =_xlfn.IFNA(VLOOKUP(_xlfn.CONCAT(K41,L41),'Bank Data'!$CH$3:$CI$1508,2,0),"") | S41: FEMALE | T41: MARRIED | V41: Ghana | W41: GHANA CARD | X41: GHA-001475549-5 | Y41: NKA084 | AB41: 01/06/2012 | AC41: SECRETARY | AF41: AIRPORT | AH41: AIRPORT | AI41: YES | AJ41: SALARY | AK41: GHS
A42: KENNEDY | B42: SARPONG | C42: 4132.51 | D42: G098408280031 | E42: sarpongkennedy0884@gmail.com | F42: 0202578566 | I42: EMPLOYEE | M42: =_xlfn.IFNA(VLOOKUP(_xlfn.CONCAT(K42,L42),'Bank Data'!$CH$3:$CI$1508,2,0),"") | S42: MALE | T42: MARRIED | V42: Ghana | W42: GHANA CARD | X42: GHA-726736128-4 | Y42: NKA102 | AB42: 04/03/2013 | AC42: CHECK IN OFFICER | AF42: AIRPORT | AH42: AIRPORT | AI42: YES | AJ42: SALARY | AK42: GHS
A43: YAW | B43: ANTWI | C43: 1480.61 | D43: D199012270038 | E43: antwiyaw033@gmail.com | F43: 0247827082 | I43: EMPLOYEE | M43: =_xlfn.IFNA(VLOOKUP(_xlfn.CONCAT(K43,L43),'Bank Data'!$CH$3:$CI$1508,2,0),"") | S43: MALE | T43: MARRIED | V43: Ghana | W43: GHANA CARD | X43: GHA-003831530-5 | Y43: NAF217 | AB43: 01/11/2021 | AC43: SECURITY | AF43: AFLAO | AH43: AFLAO | AI43: YES | AJ43: SALARY | AK43: GHS
A44: STEPHEN | B44: YAW NAAB | C44: 2344.51 | D44: J017711230051 | E44: stephennaab770@gmail.com | F44: 0243438013 | I44: EMPLOYEE | M44: =_xlfn.IFNA(VLOOKUP(_xlfn.CONCAT(K44,L44),'Bank Data'!$CH$3:$CI$1508,2,0),"") | S44: MALE | T44: MARRIED | V44: Ghana | Y44: NTE70 | AC44: TRAFFIC MARSHAL | AF44: TEMA - SENTRY PORTAL | AH44: TEMA - SENTRY PORTAL | AI44: YES | AJ44: SALARY | AK44: GHS
A45: ROCKSON | B45: KWAA | C45: 3594.51 | D45: G098707070058 | E45: rockson57@gmail.com | F45: 0200706596 | I45: EMPLOYEE | M45: =_xlfn.IFNA(VLOOKUP(_xlfn.CONCAT(K45,L45),'Bank Data'!$CH$3:$CI$1508,2,0),"") | S45: MALE | T45: MARRIED | V45: Ghana | W45: GHANA CARD | X45: GHA-713626677-1 | Y45: NAF117 | AB45: 02/01/2014 | AC45: CHECK IN OFFICER | AF45: AFLAO | AH45: AFLAO | AI45: YES | AJ45: SALARY | AK45: GHS
A46: LUKMANU | B46: ZAKARI | C46: 1740.06 | D46: C039004240092 | E46: lukumanu29@gmail.com | F46: 0557730119 | I46: EMPLOYEE | M46: =_xlfn.IFNA(VLOOKUP(_xlfn.CONCAT(K46,L46),'Bank Data'!$CH$3:$CI$1508,2,0),"") | S46: MALE | T46: SINGLE | V46: Ghana | W46: GHANA CARD | X46: GHA-715352082-9 | Y46: NKAT02 | AC46: TRAFFIC MARSHAL | AF46: AIRPORT | AH46: AIRPORT | AI46: YES | AJ46: SALARY | AK46: GHS
A47: RICHARD | B47: SACKEY SAKYI AKOMEA | C47: 4409 | D47: B228609130030 | E47: brainsakyi@yahoo.com | F47: 0540391123 | I47: EMPLOYEE | M47: =_xlfn.IFNA(VLOOKUP(_xlfn.CONCAT(K47,L47),'Bank Data'!$CH$3:$CI$1508,2,0),"") | S47: MALE | T47: SINGLE | V47: Ghana | W47: GHANA CARD | X47: GHA-005639978-1 | Y47: NAF126 | AB47: 03/02/2014 | AC47: IMAGE ANALYST | AF47: AIRPORT | AH47: AIRPORT | AI47: YES | AJ47: SALARY | AK47: GHS
A48: VICTORIA | B48: OPOKU SORO | C48: 5239.05 | D48: F018410080163 | E48: vicopokusoro@gmail.com | F48: 0242127950 | I48: EMPLOYEE | M48: =_xlfn.IFNA(VLOOKUP(_xlfn.CONCAT(K48,L48),'Bank Data'!$CH$3:$CI$1508,2,0),"") | S48: FEMALE | T48: MARRIED | V48: Ghana | W48: GHANA CARD | X48: GHA-713390286-9 | Y48: NTE175 | AB48: 01/11/2016 | AC48: IMAGE ANALYST | AF48: AIRPORT | AH48: AIRPORT | AI48: YES | AJ48: SALARY | AK48: GHS
A49: PRINCE | B49: AKWASI KYEREMEH | C49: 3727.99 | D49: G097409230059 | E49: princeporterkyeremeh@gmail.com | F49: 0201566608 | I49: EMPLOYEE | M49: =_xlfn.IFNA(VLOOKUP(_xlfn.CONCAT(K49,L49),'Bank Data'!$CH$3:$CI$1508,2,0),"") | S49: MALE | T49: MARRIED | V49: Ghana | W49: GHANA CARD | X49: GHA-715991896-7 | Y49: NKA106 | AB49: 04/03/2013 | AC49: TRAFFIC MARSHAL | AF49: TAKORADI | AH49: TAKORADI | AI49: YES | AJ49: SALARY | AK49: GHS
A50: GLADYS | B50: ANAMSI | C50: 5213.45 | D50: C016703230105 | E50: gladysanamsi@gmail.com | F50: 0243582100 | I50: EMPLOYEE | M50: =_xlfn.IFNA(VLOOKUP(_xlfn.CONCAT(K50,L50),'Bank Data'!$CH$3:$CI$1508,2,0),"") | S50: FEMALE | T50: MARRIED | V50: Ghana | W50: GHANA CARD | X50: GHA-001139725-6 | Y50: NTE017 | AB50: 01/04/2009 | AC50: CHECK IN OFFICER | AF50: TEMA-MAIN | AH50: TEMA-MAIN | AI50: YES | AJ50: SALARY | AK50: GHS
A51: FRANCIS | B51: OFORI KWAKU | C51: 4254.51 | D51: C018107150238 | E51: willkommenn1@gmail.com | F51: 0264103041 | I51: EMPLOYEE | M51: =_xlfn.IFNA(VLOOKUP(_xlfn.CONCAT(K51,L51),'Bank Data'!$CH$3:$CI$1508,2,0),"") | S51: MALE | T51: MARRIED | V51: Ghana | W51: GHANA CARD | X51: GHA-726530111-6 | Y51: NKA090 | AB51: 03/09/2012 | AC51: CHECK IN OFFICER | AF51: Head Office | AH51: Head Office | AI51: YES | AJ51: SALARY | AK51: GHS
A52: PRINCE | B52: SORO | C52: 8341.51 | D52: F018012100010 | E52: soroprince@yahoo.com | F52: 0244637316 | I52: EMPLOYEE | M52: =_xlfn.IFNA(VLOOKUP(_xlfn.CONCAT(K52,L52),'Bank Data'!$CH$3:$CI$1508,2,0),"") | S52: MALE | T52: MARRIED | V52: Ghana | W52: GHANA CARD | X52: GHA-713383828-5 | Y52: NTE009 | AB52: 01/08/2007 | AC52: IMAGE ANALYST | AF52: TEMA MAIN | AH52: TEMA MAIN | AI52: YES | AJ52: SALARY | AK52: GHS
A53: JOSHUA | B53: ASARE | C53: 3283.91 | D53: C018805170215 | E53: asarejosh2022@gmail.com | F53: 0261201640 | I53: EMPLOYEE | M53: =_xlfn.IFNA(VLOOKUP(_xlfn.CONCAT(K53,L53),'Bank Data'!$CH$3:$CI$1508,2,0),"") | S53: MALE | V53: Ghana | W53: GHANA CARD | X53: GHA-001106598-4 | Y53: NKA109 | AB53: 04/03/2013 | AC53: TRAFFIC MARSHAL | AF53: AIRPORT | AH53: AIRPORT | AI53: YES | AJ53: SALARY | AK53: GHS
A54: JEFFREY | B54: DADSON | C54: 3391.54 | D54: C019208090833 | E54: jeffdadson@gmail.com | F54: 0574834107 | I54: EMPLOYEE | M54: =_xlfn.IFNA(VLOOKUP(_xlfn.CONCAT(K54,L54),'Bank Data'!$CH$3:$CI$1508,2,0),"") | S54: MALE | T54: SINGLE | V54: Ghana | W54: GHANA CARD | X54: GHA-000456014-0 | Y54: NKA215 | AB54: 01/11/2021 | AC54: IMAGE ANALYST | AF54: AIRPORT | AH54: AIRPORT | AI54: YES | AJ54: SALARY | AK54: GHS
A55: AKWESI | B55: AMPONSAH | C55: 1737.57 | E55: akasim680@gmail.com | F55: 0544280289 | I55: EMPLOYEE | M55: =_xlfn.IFNA(VLOOKUP(_xlfn.CONCAT(K55,L55),'Bank Data'!$CH$3:$CI$1508,2,0),"") | S55: MALE | T55: MARRIED | V55: Ghana | W55: GHANA CARD | X55: GHA-713972848-7 | Y55: NAF216 | AB55: 01/11/2021 | AC55: SECURITY | AF55: AFLAO | AH55: AFLAO | AI55: YES | AJ55: SALARY | AK55: GHS
A56: NELSON | B56: ANKOMAH | C56: 2917.91 | D56: G097908220016 | E56: nelsonankomah190@gmail.com | F56: 0548998394 | I56: EMPLOYEE | M56: =_xlfn.IFNA(VLOOKUP(_xlfn.CONCAT(K56,L56),'Bank Data'!$CH$3:$CI$1508,2,0),"") | S56: MALE | V56: Ghana | W56: GHANA CARD | X56: GHA-725670881-4 | Y56: NKA138 | AB56: 01/06/2015 | AC56: TRAFFIC MARSHAL | AF56: AIRPORT | AH56: AIRPORT | AI56: YES | AJ56: SALARY | AK56: GHS
A57: ENOCH | B57: KOFI ANNAN | C57: 2027.21 | D57: E109211020017 | E57: enochannan20@gmail.com | F57: 0244902030 | I57: EMPLOYEE | M57: =_xlfn.IFNA(VLOOKUP(_xlfn.CONCAT(K57,L57),'Bank Data'!$CH$3:$CI$1508,2,0),"") | S57: MALE | T57: SINGLE | V57: Ghana | W57: GHANA CARD | X57: GHA-718952411-6 | Y57: NTA230 | AC57: CHECK IN OFFICER | AF57: TAKORADI | AH57: TAKORADI | AI57: YES | AJ57: SALARY | AK57: GHS
A58: COSMOS | B58: KWABENA AGYAKWA | C58: 2795.91 | D58: C017911200412 | E58: cagyakwa@gmail.com | F58: 0261228082 | I58: EMPLOYEE | M58: =_xlfn.IFNA(VLOOKUP(_xlfn.CONCAT(K58,L58),'Bank Data'!$CH$3:$CI$1508,2,0),"") | S58: MALE | T58: MARRIED | V58: Ghana | W58: GHANA CARD | X58: GHA-728123732-5 | Y58: NTE199 | AB58: 03/07/2019 | AC58: TRAFFIC MARSHAL | AF58: TEMA - SENTRY PORTAL | AH58: TEMA - SENTRY PORTAL | AI58: YES | AJ58: SALARY | AK58: GHS
A59: SANDRA | B59: OWUSU | C59: 3391.54 | D59: G099311110023 | E59: sandyyadepa9@gmail.com | F59: 0549379028 | I59: EMPLOYEE | M59: =_xlfn.IFNA(VLOOKUP(_xlfn.CONCAT(K59,L59),'Bank Data'!$CH$3:$CI$1508,2,0),"") | S59: FEMALE | V59: Ghana | W59: GHANA CARD | X59: GHA-727449502-2 | Y59: NKA210 | AB59: 01/11/2021 | AC59: CHECK IN OFFICER | AF59: AIRPORT | AH59: AIRPORT | AI59: YES | AJ59: SALARY | AK59: GHS
A60: MICHAEL | B60: TETTEH TWUMASI | C60: 5185.35 | D60: G098710240011 | E60: twumasimichael@yahoo.com | F60: 0244213275 | I60: EMPLOYEE | M60: =_xlfn.IFNA(VLOOKUP(_xlfn.CONCAT(K60,L60),'Bank Data'!$CH$3:$CI$1508,2,0),"") | S60: MALE | T60: MARRIED | V60: Ghana | W60: GHANA CARD | X60: GHA-715285170-8 | Y60: NKA082 | AB60: 01/06/2012 | AC60: CHECK IN OFFICER | AF60: AIRPORT | AH60: AIRPORT | AI60: YES | AJ60: SALARY | AK60: GHS
A61: ROGER | B61: ADJEI | C61: 4292.85 | D61: C018404050418 | E61: adjei_roger2000@yahoo.com | F61: 0246743749 | I61: EMPLOYEE | M61: =_xlfn.IFNA(VLOOKUP(_xlfn.CONCAT(K61,L61),'Bank Data'!$CH$3:$CI$1508,2,0),"") | S61: MALE | T61: MARRIED | V61: Ghana | W61: GHANA CARD | X61: GHA-000722479-1 | Y61: NTE131 | AB61: 02/06/2014 | AC61: CHECK IN OFFICER | AF61: TAKORADI | AH61: TAKORADI | AI61: YES | AJ61: SALARY | AK61: GHS
A62: KETOR | B62: ALEXANDER | C62: 12988.37 | D62: C037209120030 | E62: setoraexander@yahoo.com | F62: 0546415946 | I62: EMPLOYEE | M62: =_xlfn.IFNA(VLOOKUP(_xlfn.CONCAT(K62,L62),'Bank Data'!$CH$3:$CI$1508,2,0),"") | S62: MALE | T62: MARRIED | V62: Ghana | W62: GHANA CARD | X62: GHA-720190044-9 | Y62: NTA028 | AB62: 01/08/2007 | AC62: TAKORADI MANAGER | AF62: TAKORADI | AH62: TAKORADI | AI62: YES | AJ62: SALARY | AK62: GHS
A63: WILLIAMS | B63: ANTWI | C63: 2344.51 | D63: 06A22D07238 | E63: Antwiwilliams525@gmail.com | F63: 0544015554 | I63: EMPLOYEE | M63: =_xlfn.IFNA(VLOOKUP(_xlfn.CONCAT(K63,L63),'Bank Data'!$CH$3:$CI$1508,2,0),"") | S63: MALE | T63: MARRIED | V63: Ghana | W63: GHANA CARD | X63: GHA-716407904-2 | Y63: NKA228 | AC63: TRAFFIC MARSHAL | AF63: AIRPORT | AH63: AIRPORT | AI63: YES | AJ63: SALARY | AK63: GHS
A64: KINGSLEY | B64: BADU | C64: 3954.91 | D64: G017801060031 | E64: kingsleykofibadu@gmail.com | F64: 0246724528 | I64: EMPLOYEE | M64: =_xlfn.IFNA(VLOOKUP(_xlfn.CONCAT(K64,L64),'Bank Data'!$CH$3:$CI$1508,2,0),"") | S64: MALE | V64: Ghana | W64: GHANA CARD | X64: GHA-718890325-9 | Y64: NTA039 | AB64: 01/08/2007 | AC64: SECURITY | AF64: TAKORADI | AH64: TAKORADI | AI64: YES | AJ64: SALARY | AK64: GHS
A65: DANIEL | B65: WETAANE APEWURU | C65: 1591.17 | D65: J138807090014 | E65: wetaaned@gmail.com | F65: 0247462720 | I65: EMPLOYEE | M65: =_xlfn.IFNA(VLOOKUP(_xlfn.CONCAT(K65,L65),'Bank Data'!$CH$3:$CI$1508,2,0),"") | S65: MALE | V65: Ghana | W65: GHANA CARD | X65: GHA-716341987-0 | Y65: NPA231 | AC65: CHECK IN OFFICER | AF65: PAGA | AH65: PAGA | AI65: YES | AJ65: SALARY | AK65: GHS
A66: CHRISTIANA | B66: ADU AGYEIWAA | C66: 5091.45 | D66: G098705050047 | E66: chriskasadu71@gmail.com | F66: 0201199899 | I66: EMPLOYEE | M66: =_xlfn.IFNA(VLOOKUP(_xlfn.CONCAT(K66,L66),'Bank Data'!$CH$3:$CI$1508,2,0),"") | S66: FEMALE | T66: MARRIED | V66: Ghana | W66: GHANA CARD | X66: GHA-005622464-7 | Y66: NTE018 | AB66: 01/11/2011 | AC66: CHECK IN OFFICER | AF66: TEMA MAIN | AH66: TEMA MAIN | AI66: YES | AJ66: SALARY | AK66: GHS
A67: KULU | B67: SEIDU AYARIGA | C67: 5180.51 | D67: J018309240060 | E67: alzayaan13@yahoo.com | F67: 0244122424 | I67: EMPLOYEE | M67: =_xlfn.IFNA(VLOOKUP(_xlfn.CONCAT(K67,L67),'Bank Data'!$CH$3:$CI$1508,2,0),"") | S67: FEMALE | T67: MARRIED | V67: Ghana | W67: GHANA CARD | X67: GHA-001150598-7 | Y67: NTE016 | AB67: 15/05/2008 | AC67: CHECK IN OFFICER | AF67: TEMA MAIN | AH67: TEMA MAIN | AI67: YES | AJ67: SALARY | AK67: GHS
A68: SAMPSON | B68: OPOKU | C68: 2795.91 | D68: G098505070038 | E68: opokusampsom676@gmail.com | F68: 0203502809 | I68: EMPLOYEE | M68: =_xlfn.IFNA(VLOOKUP(_xlfn.CONCAT(K68,L68),'Bank Data'!$CH$3:$CI$1508,2,0),"") | S68: MALE | T68: MARRIED | V68: Ghana | W68: GHANA CARD | X68: GHA-715595001-5 | Y68: NTE168 | AB68: 01/10/2016 | AC68: TRAFFIC MARSHAL | AF68: TEMA - SENTRY PORTAL | AH68: TEMA - SENTRY PORTAL | AI68: YES | AJ68: SALARY | AK68: GHS
A69: RABIATU | B69: MARLLE | C69: 5435 | D69: F218810130028 | E69: rmarlle.marlle@gmail.com | F69: 0277802418 | I69: EMPLOYEE | M69: =_xlfn.IFNA(VLOOKUP(_xlfn.CONCAT(K69,L69),'Bank Data'!$CH$3:$CI$1508,2,0),"") | S69: FEMALE | T69: MARRIED | V69: Ghana | W69: GHANA CARD | X69: GHA-002470352-3 | Y69: NKA128 | AB69: 01/04/2014 | AC69: IMAGE AUDITOR | AF69: TEMA MAIN | AH69: TEMA MAIN | AI69: YES | AJ69: SALARY | AK69: GHS
A70: KWADWO | B70: OHENE BAFFOE KRAPIM | C70: 4969.45 | D70: G098510100014 | E70: krapim1@gmail.com | F70: 0244866732 | I70: EMPLOYEE | M70: =_xlfn.IFNA(VLOOKUP(_xlfn.CONCAT(K70,L70),'Bank Data'!$CH$3:$CI$1508,2,0),"") | S70: MALE | T70: MARRIED | V70: Ghana | W70: GHANA CARD | X70: GHA-713301323-3 | Y70: NTE020 | AB70: 01/11/2011 | AC70: IMAGE ANALYST | AF70: TEMA MAIN | AH70: TEMA MAIN | AI70: YES | AJ70: SALARY | AK70: GHS
A71: MICHAEL | B71: ASIEDU NTOW | C71: 5263.45 | D71: E128410190016 | E71: mnasiedu13@yahoo.com | F71: 0275085133 | I71: EMPLOYEE | M71: =_xlfn.IFNA(VLOOKUP(_xlfn.CONCAT(K71,L71),'Bank Data'!$CH$3:$CI$1508,2,0),"") | S71: MALE | T71: SINGLE | V71: Ghana | W71: GHANA CARD | X71: GHA-001705061-8 | Y71: NKA078 | AB71: 01/06/2016 | AC71: IMAGE ANALYST | AF71: AIRPORT | AH71: AIRPORT | AI71: YES | AJ71: SALARY | AK71: GHS
A72: KWABENA | B72: ADJEI | C72: 3421.25 | D72: G098510290014 | E72: nanaadjeisika@gmail.com | F72: 0249180711 | I72: EMPLOYEE | M72: =_xlfn.IFNA(VLOOKUP(_xlfn.CONCAT(K72,L72),'Bank Data'!$CH$3:$CI$1508,2,0),"") | S72: MALE | T72: SINGLE | V72: Ghana | W72: GHANA CARD | X72: GHA-726215083-6 | Y72: NTA037 | AC72: CHECK IN OFFICER | AF72: TEMA - SENTRY PORTAL | AH72: TEMA - SENTRY PORTAL | AI72: YES | AJ72: SALARY | AK72: GHS
A73: ABUKARI | B73: ZAKARI | C73: 3771.91 | D73: J058209040038 | E73: wronnie600@gmail.com | F73: 0247298533 | I73: EMPLOYEE | M73: =_xlfn.IFNA(VLOOKUP(_xlfn.CONCAT(K73,L73),'Bank Data'!$CH$3:$CI$1508,2,0),"") | S73: MALE | T73: SINGLE | V73: Ghana | W73: GHANA CARD | X73: GHA-725631201-1 | Y73: NAF049 | AB73: 01/11/2011 | AC73: TRAFFIC MARSHAL | AF73: TEMA - SENTRY PORTAL | AH73: TEMA - SENTRY PORTAL | AI73: YES | AJ73: SALARY | AK73: GHS
A74: CHARLES | B74: SAMPENE | C74: 4015.91 | E74: charlessampene@gmail.com | F74: 0243567928 | I74: EMPLOYEE | M74: =_xlfn.IFNA(VLOOKUP(_xlfn.CONCAT(K74,L74),'Bank Data'!$CH$3:$CI$1508,2,0),"") | S74: MALE | V74: Ghana | W74: GHANA CARD | X74: GHA-719159808-8 | Y74: NTA038 | AB74: 01/08/2007 | AC74: TRAFFIC MARSHAL | AF74: TAKORADI | AH74: TAKORADI | AI74: YES | AJ74: SALARY | AK74: GHS
A75: JUSTICE | B75: KOOMSON | C75: 3893.91 | D75: A017908160134 | E75: justkoomson25@gmail.com | F75: 0277753860 | I75: EMPLOYEE | M75: =_xlfn.IFNA(VLOOKUP(_xlfn.CONCAT(K75,L75),'Bank Data'!$CH$3:$CI$1508,2,0),"") | S75: MALE | V75: Ghana | W75: GHANA CARD | X75: GHA-718819635-4 | Y75: NTA042 | AB75: 01/08/2007 | AC75: OFFICE ASSISTANT | AF75: TAKORADI | AH75: TAKORADI | AI75: YES | AJ75: SALARY | AK75: GHS
A76: ALEX | B76: SAKYI | C76: 4865.91 | D76: G098107210034 | E76: opegasty34nkz@gmail.com | F76: 0244123366 | I76: EMPLOYEE | M76: =_xlfn.IFNA(VLOOKUP(_xlfn.CONCAT(K76,L76),'Bank Data'!$CH$3:$CI$1508,2,0),"") | S76: MALE | V76: Ghana | W76: GHANA CARD | X76: GHA-727783197-5 | Y76: NKA072 | AB76: 01/09/2011 | AC76: DRIVER | AF76: GHANA LINK | AH76: GHANA LINK | AI76: YES | AJ76: SALARY | AK76: GHS
A77: KWABENA | B77: OPOKU AGYEMAN | C77: 3727.99 | D77: G099010050014 | E77: kpoku3015@gmail.com | F77: 0243059106 | I77: EMPLOYEE | M77: =_xlfn.IFNA(VLOOKUP(_xlfn.CONCAT(K77,L77),'Bank Data'!$CH$3:$CI$1508,2,0),"") | S77: MALE | V77: Ghana | W77: GHANA CARD | X77: GHA-728596717-8 | Y77: NKA067 | AB77: 01/11/2011 | AC77: TRAFFIC MARSHAL | AF77: AIRPORT | AH77: AIRPORT | AI77: YES | AJ77: SALARY | AK77: GHS
A78: ENOCH | B78: ZANZY AMPONSAH | C78: 3804.85 | D78: C018103100498 | E78: degreatzany@gmail.com | F78: 0201549400 | I78: EMPLOYEE | M78: =_xlfn.IFNA(VLOOKUP(_xlfn.CONCAT(K78,L78),'Bank Data'!$CH$3:$CI$1508,2,0),"") | S78: MALE | V78: Ghana | W78: GHANA CARD | X78: GHA-713671880-9 | Y78: NKA061 | AB78: 01/11/2011 | AC78: TRAFFIC MARSHAL | AF78: AFLAO | AH78: AFLAO | AI78: YES | AJ78: SALARY | AK78: GHS
A79: THEOPHILUS | B79: KABUTEY | C79: 3316.85 | D79: C038011040054 | I79: EMPLOYEE | M79: =_xlfn.IFNA(VLOOKUP(_xlfn.CONCAT(K79,L79),'Bank Data'!$CH$3:$CI$1508,2,0),"") | S79: MALE | T79: SINGLE | V79: Ghana | W79: GHANA CARD | X79: GHA-001052812-7 | Y79: NTE155 | AC79: DRIVER | AF79: GHANA LINK | AH79: GHANA LINK | AI79: YES | AJ79: SALARY | AK79: GHS
A80: GRACE | B80: BAWUAH | C80: 3354.94 | D80: C039105250085 | E80: gracie2514@yahoo.com | F80: 0209954911 | I80: EMPLOYEE | M80: =_xlfn.IFNA(VLOOKUP(_xlfn.CONCAT(K80,L80),'Bank Data'!$CH$3:$CI$1508,2,0),"") | S80: FEMALE | T80: SINGLE | V80: Ghana | W80: GHANA CARD | X80: GHA-728118959-6 | Y80: NKA212 | AB80: 01/11/2011 | AC80: CHECK IN OFFICER | AF80: AIRPORT | AH80: AIRPORT | AI80: YES | AJ80: SALARY | AK80: GHS
A81: PETER | B81: NASH | C81: 2917.91 | D81: C018004010914 | E81: nashpeter119@gmail.com | F81: 0554753494 | I81: EMPLOYEE | M81: =_xlfn.IFNA(VLOOKUP(_xlfn.CONCAT(K81,L81),'Bank Data'!$CH$3:$CI$1508,2,0),"") | S81: MALE | T81: SINGLE | V81: Ghana | W81: GHANA CARD | X81: GHA-713426566-4 | Y81: NTA040 | AB81: 03/03/2014 | AC81: DRIVER | AF81: TEMA MAIN | AH81: TEMA MAIN | AI81: YES | AJ81: SALARY | AK81: GHS
A82: MABEL | B82: AFUA MENSAH SOLOMON | C82: 3391.54 | D82: C019206050844 | E82: mabelsolomon92@gmail.com | F82: 0207494592 | I82: EMPLOYEE | M82: =_xlfn.IFNA(VLOOKUP(_xlfn.CONCAT(K82,L82),'Bank Data'!$CH$3:$CI$1508,2,0),"") | S82: FEMALE | T82: MARRIED | V82: Ghana | W82: GHANA CARD | X82: GHA-713043962-7 | Y82: NKA213 | AB82: 01/11/2011 | AC82: IMAGE ANALYST | AF82: AIRPORT | AH82: AIRPORT | AI82: YES | AJ82: SALARY | AK82: GHS
A83: HARUNA | B83: MAHAMA | C83: 10149.53 | D83: H137604070012 | E83: mahama.haruna@gmail.com | F83: 0243313113 | I83: EMPLOYEE | M83: =_xlfn.IFNA(VLOOKUP(_xlfn.CONCAT(K83,L83),'Bank Data'!$CH$3:$CI$1508,2,0),"") | S83: MALE | T83: MARRIED | V83: Ghana | W83: GHANA CARD | Y83: NKA053 | AB83: 01/11/2011 | AC83: MANAGER PAGA | AF83: PAGA | AH83: PAGA | AI83: YES | AJ83: SALARY | AK83: GHS
A84: COMFORT | B84: AHINKURAH | C84: 9028.85 | D84: C017207170144 | I84: EMPLOYEE | M84: =_xlfn.IFNA(VLOOKUP(_xlfn.CONCAT(K84,L84),'Bank Data'!$CH$3:$CI$1508,2,0),"") | S84: FEMALE | T84: MARRIED | V84: Ghana | W84: GHANA CARD | Y84: NTAD01 | AC84: DIRECTOR Of WELFARE | AF84: Head Office | AH84: Head Office | AI84: YES | AJ84: SALARY | AK84: GHS
A85: BISMARK | B85: SARKODIE | C85: 3191.91 | D85: F018711110453 | E85: slysark1@gmail.com | F85: 0207282728 | I85: EMPLOYEE | M85: =_xlfn.IFNA(VLOOKUP(_xlfn.CONCAT(K85,L85),'Bank Data'!$CH$3:$CI$1508,2,0),"") | S85: MALE | V85: Ghana | W85: GHANA CARD | X85: GHA-713580297-2 | Y85: NAF120 | AB85: 02/01/2014 | AC85: TRAFFIC MARSHAL | AF85: AFLAO | AH85: AFLAO | AI85: YES | AJ85: SALARY | AK85: GHS
A86: ROBERT | B86: KWAME BOMBEYANG | C86: 4292.85 | D86: C037801070070 | E86: kwamerobert07@gmail.com | F86: 0244613447 | I86: EMPLOYEE | M86: =_xlfn.IFNA(VLOOKUP(_xlfn.CONCAT(K86,L86),'Bank Data'!$CH$3:$CI$1508,2,0),"") | S86: MALE | T86: MARRIED | V86: Ghana | W86: GHANA CARD | X86: GHA-715770442-7 | Y86: NTE024 | AB86: 02/01/2004 | AC86: TRAFFIC MARSHAL | AF86: PAGA | AH86: PAGA | AI86: YES | AJ86: SALARY | AK86: GHS
A87: DANIEL | B87: AMOLKUNA | C87: 3405.91 | D87: J018211020037 | F87: 0249909586 | I87: EMPLOYEE | M87: =_xlfn.IFNA(VLOOKUP(_xlfn.CONCAT(K87,L87),'Bank Data'!$CH$3:$CI$1508,2,0),"") | S87: MALE | T87: MARRIED | V87: Ghana | W87: GHANA CARD | X87: GHA-721054937-4 | Y87: NKA074 | AB87: 01/06/2012 | AC87: OFFICE ASSISTANT | AF87: TAKORADI | AH87: TAKORADI | AI87: YES | AJ87: SALARY | AK87: GHS
A88: FAROUK | B88: MOHAMMED | C88: 1480.61 | D88: J138709270032 | E88: pwabaduwafk2@gmail.com | F88: 0244873791 | I88: EMPLOYEE | M88: =_xlfn.IFNA(VLOOKUP(_xlfn.CONCAT(K88,L88),'Bank Data'!$CH$3:$CI$1508,2,0),"") | S88: MALE | V88: Ghana | W88: GHANA CARD | X88: GHA-715982402-4 | Y88: NPA223 | AB88: 01/11/2021 | AC88: TRAFFIC MARSHAL | AF88: PAGA | AH88: PAGA | AI88: YES | AJ88: SALARY | AK88: GHS
A89: HERTY | B89: ADDAI | C89: 3505.45 | D89: B017712130028 | E89: Hertyaddai@gmail.com | F89: 0244158691 | I89: EMPLOYEE | M89: =_xlfn.IFNA(VLOOKUP(_xlfn.CONCAT(K89,L89),'Bank Data'!$CH$3:$CI$1508,2,0),"") | S89: MALE | T89: MARRIED | V89: Ghana | W89: GHANA CARD | X89: GHA-725563758-4 | Y89: NTE107 | AB89: 04/03/2013 | AC89: OFFICE ASSISTANT | AF89: AIRPORT | AH89: AIRPORT | AI89: YES | AJ89: SALARY | AK89: GHS
A90: RAYMOND | B90: TAYLOR | C90: 1371.59 | D90: B108911290013 | E90: taylorraymond946@gmail.com | F90: 0278577004 | I90: EMPLOYEE | M90: =_xlfn.IFNA(VLOOKUP(_xlfn.CONCAT(K90,L90),'Bank Data'!$CH$3:$CI$1508,2,0),"") | S90: MALE | T90: MARRIED | V90: Ghana | W90: GHANA CARD | X90: GHA-000983639-2 | Y90: NTE219 | AB90: 01/11/2021 | AC90: TRAFFIC MARSHAL | AF90: TEMA - SENTRY PORTAL | AH90: TEMA - SENTRY PORTAL | AI90: YES | AJ90: SALARY | AK90: GHS
A91: MUHAYIDEEN | B91: ABUBAKAR | C91: 4287 | D91: H088202150035 | E91: muhayideen123@gmail.com | F91: 0244144080 | I91: EMPLOYEE | M91: =_xlfn.IFNA(VLOOKUP(_xlfn.CONCAT(K91,L91),'Bank Data'!$CH$3:$CI$1508,2,0),"") | S91: MALE | T91: MARRIED | V91: Ghana | W91: GHANA CARD | X91: GHA-712289091-1 | Y91: NKA100 | AB91: 04/03/2013 | AC91: IMAGE ANALYST | AF91: TEMA - SENTRY PORTAL | AH91: TEMA - SENTRY PORTAL | AI91: YES | AJ91: SALARY | AK91: GHS
A92: HERMANN | B92: J. C. HESSE | C92: 4287 | D92: C018009030474 | E92: hjchesse@yahoo.com | F92: 0244381715 | I92: EMPLOYEE | M92: =_xlfn.IFNA(VLOOKUP(_xlfn.CONCAT(K92,L92),'Bank Data'!$CH$3:$CI$1508,2,0),"") | S92: MALE | T92: MARRIED | V92: Ghana | W92: GHANA CARD | X92: GHA-002225554-7 | Y92: NTE142 | AB92: 03/08/2015 | AC92: IMAGE ANALYST | AF92: AIRPORT | AH92: AIRPORT | AI92: YES | AJ92: SALARY | AK92: GHS
A93: PROSPER | B93: KWAME WIAFE | C93: 3893.91 | D93: G097901130010 | E93: kwamewaife03@gmail.com | F93: 0243048703 | I93: EMPLOYEE | M93: =_xlfn.IFNA(VLOOKUP(_xlfn.CONCAT(K93,L93),'Bank Data'!$CH$3:$CI$1508,2,0),"") | S93: MALE | T93: MARRIED | V93: Ghana | W93: GHANA CARD | X93: GHA-001052974-0 | Y93: NTE022 | AC93: SYSTEM OPERATOR | AF93: TEMA - SENTRY PORTAL | AH93: TEMA - SENTRY PORTAL | AI93: YES | AJ93: SALARY | AK93: GHS
A94: ISAAC | B94: NARH AYIKU | C94: 7306.11 | D94: C017708190236 | E94: ayiisa112@gmail.com | F94: 0277457574 | I94: EMPLOYEE | M94: =_xlfn.IFNA(VLOOKUP(_xlfn.CONCAT(K94,L94),'Bank Data'!$CH$3:$CI$1508,2,0),"") | S94: MALE | T94: MARRIED | V94: Ghana | W94: GHANA CARD | X94: GHA-712562559-6 | Y94: NTA031 | AB94: 01/08/2007 | AC94: MAINTENANCE | AF94: TEMA MAIN | AH94: TEMA MAIN | AI94: YES | AJ94: SALARY | AK94: GHS
A95: SHEILA | B95: BAFFOE KUSI | C95: 4847 | D95: G097908250028 | E95: sheilaawusuansah@gmail.com | F95: 0249703020 | I95: EMPLOYEE | M95: =_xlfn.IFNA(VLOOKUP(_xlfn.CONCAT(K95,L95),'Bank Data'!$CH$3:$CI$1508,2,0),"") | S95: FEMALE | T95: MARRIED | V95: Ghana | W95: GHANA CARD | X95: GHA-719153514-0 | Y95: NTA032 | AB95: 01/08/2007 | AC95: SECRETARY | AF95: TAKORADI | AH95: TAKORADI | AI95: YES | AJ95: SALARY | AK95: GHS
A96: SANDRA | B96: BOATEMA BOAHENE | C96: 7840.48 | D96: C038405170103 | E96: sandraboahene@nickscan.com | F96: 0243347977 | I96: EMPLOYEE | M96: =_xlfn.IFNA(VLOOKUP(_xlfn.CONCAT(K96,L96),'Bank Data'!$CH$3:$CI$1508,2,0),"") | S96: FEMALE | T96: SINGLE | V96: Ghana | W96: GHANA CARD | X96: GHA-713509853-3 | Y96: NTE019 | AB96: 01/08/2011 | AC96: ASSISTANT HUMAN RESOURCE MANAGER | AF96: TEMA MAIN | AH96: TEMA MAIN | AI96: YES | AJ96: SALARY | AK96: GHS
A97: ISAAC | B97: DWAMENAH | C97: 4692.51 | D97: C108110010019 | E97: idwamenah@gmail.com | F97: 0206959664 | I97: EMPLOYEE | M97: =_xlfn.IFNA(VLOOKUP(_xlfn.CONCAT(K97,L97),'Bank Data'!$CH$3:$CI$1508,2,0),"") | S97: MALE | T97: MARRIED | V97: Ghana | W97: GHANA CARD | X97: GHA-001111942-5 | Y97: NKA135 | AB97: 02/02/2015 | AC97: CARGO INSPECTION OFFICER | AF97: AIRPORT | AH97: AIRPORT | AI97: YES | AJ97: SALARY | AK97: GHS
A98: KWAME | B98: ANKOMAH | C98: 2862.51 | D98: G098610100030 | E98: ankomahkwame87@gmail.com | F98: 0554599123 | I98: EMPLOYEE | M98: =_xlfn.IFNA(VLOOKUP(_xlfn.CONCAT(K98,L98),'Bank Data'!$CH$3:$CI$1508,2,0),"") | S98: MALE | V98: Ghana | W98: GHANA CARD | X98: GHA-720954648-3 | Y98: NTA182 | AB98: 02/05/2017 | AC98: CHECK IN OFFICER | AF98: TEMA MAIN | AH98: TEMA MAIN | AI98: YES | AJ98: SALARY | AK98: GHS
A99: ALFRED | B99: MENSAH BONSU | C99: 3138.73 | D99: F018006020251 | E99: alfredbonsu5@gmail.com | F99: 0244375011 | I99: EMPLOYEE | M99: =_xlfn.IFNA(VLOOKUP(_xlfn.CONCAT(K99,L99),'Bank Data'!$CH$3:$CI$1508,2,0),"") | S99: MALE | T99: MARRIED | V99: Ghana | W99: GHANA CARD | X99: GHA-727345840-0 | Y99: NKA166 | AB99: 01/09/2016 | AC99: TRAFFIC MARSHAL | AF99: AIRPORT | AH99: AIRPORT | AI99: YES | AJ99: SALARY | AK99: GHS
A100: KWAKU | B100: OBENG AGYEI DANQUAH | C100: 5851.89 | D100: C017809250391 | E100: kwekudanquah@gmail.com | F100: 0244474127 | I100: EMPLOYEE | M100: =_xlfn.IFNA(VLOOKUP(_xlfn.CONCAT(K100,L100),'Bank Data'!$CH$3:$CI$1508,2,0),"") | S100: MALE | T100: MARRIED | V100: Ghana | W100: GHANA CARD | X100: GHA-002455688-0 | Y100: NKA149 | AB100: 15/05/2015 | AC100: IMAGE ANALYST | AF100: AIRPORT | AH100: AIRPORT | AI100: YES | AJ100: SALARY | AK100: GHS
...

Sheet Bank Data
A2: BankName | C2: Absa (GH) LTD Branches | D2: Absa (GH) LTD BankBranchCode | F2: Access Bank (Ghana) Plc Branches | G2: Access Bank (Ghana) Plc BankBranchCode | I2: Agricultural Development Bank Limited Branches | J2: Agricultural Development Bank Limited BankBranchCode | L2: Apex Bank GH Limited Branches | M2: Apex Bank GH Limited BankBranchCode | O2: Bank of Africa Ghana Limited | P2: Bank of Africa Ghana Limited BankBranchCode | R2: Bank of Ghana | S2: Bank of Ghana BankBranchCode | U2: BSIC Ghana Limited | V2: BSIC Ghana Limited BankBranchCode | X2: CAL Bank Limited | Y2: CAL Bank Limited BankBranchCode | AA2: Consolidated Bank Ghana Limited | AB2: Consolidated Bank Ghana Limited BankBranchCode | AD2: Ecobank Ghana Limited | AE2: Ecobank Ghana Limited BankBranchCode | AG2: FBN Bank (Ghana) Limited | AH2: FBN Bank (Ghana) Limited BankBranchCode | AJ2: Fidelity Bank Limited | AK2: Fidelity Bank Limited BankBranchCode | AM2: First Atlantic Bank Limited | AN2: First Atlantic Bank Limited BankBranchCode | AP2: First National Bank (Ghana) Limited | AQ2: First National Bank (Ghana) Limited | AS2: GCB Bank Limited | AT2: GCB Bank Limited BankBranchCode | AV2: GHL Bank Limited | AW2: GHL Bank Limited BankBranchCode | AZ2: Guaranty Trust Bank (Ghana) Limited | BA2: Guaranty Trust Bank (Ghana) Limited BankBranchCode | BC2: National Investment Bank Limited | BD2: National Investment Bank Limited BankBranchCode | BF2: Omni Bank Ghana Limited | BG2: Omni Bank Ghana Limited BankBranchCode | BI2: Prudential Bank Limited | BJ2: Prudential Bank Limited BankBranchCode | BL2: Republic Bank (Ghana) Limited | BM2: Republic Bank (Ghana) Limited BankBranchCode | BO2: Societe General (Ghana) Limited | BP2: Societe General (Ghana) Limited BankBranchCode | BR2: Stanbic Bank Ghana Limited | BS2: Stanbic Bank Ghana Limited BankBranchCode | BU2: Standard Chartered Bank (Ghana) Limited | BV2: Standard Chartered Bank (Ghana) Limited BankBranchName | BX2: United Bank for Africa (Ghana) Limited | BY2: United Bank for Africa (Ghana) Limited BankBranchCode | CA2: Universal Merchant Bank Limited | CB2: Universal Merchant Bank Limited BankBranchCode | CD2: Zenith Bank (Ghana) Limited | CE2: Zenith Bank (Ghana) Limited BankBranchCode | CH2: ALL BANK BRANCHES | CI2: BRANCH CODE
A3: Absa (GH) LTD | C3: BARCLAYS BANK OF GHANA LIMITED | D3: 30100 | F3: HEAD OFFICE | G3: 280100 | I3: CORPORATE BANKING | J3: 80010 | L3: ARB APEX BANK/RURAL & COMMUNITY BANKS | M3: 70100 | O3: HEAD OFFICE | P3: 210100 | R3: HEAD OFFICE | S3: 10100 | U3: BSIC BANK | V3: 270100 | X3: HEAD OFFICE | Y3: 140100 | AA3: HEAD OFFICE | AB3: 340100 | AD3: ECOBANK GHANA LIMITED | AE3: 130100 | AG3: FBN BANK (GHANA) LIMITED | AH3: 200100 | AJ3: WOMEN'S WORLD BANK GHANA SAVINGS AND LOANS | AK3: 170170 | AM3: FIRST ATLANTIC BANK LIMITED | AN3: 170100 | AP3: FIRST ATLANTIC BANK LTD - GLOBAL ACCESS S-L | AQ3: 170178 | AS3: WA | AT3: 40001 | AV3: HEAD OFFICE | AW3: 390100 | AZ3: GUARANTY TRUST BANK (GHANA) LIMITED | BA3: 230100 | BC3: NATIONAL INVESTMENT BANK | BD3: 50100 | BF3: OMNI BANK GHANA LIMITED | BG3: 360100 | BI3: PRUDENTIAL BANK | BJ3: 180100 | BL3: REPUBLIC BANK (GHANA) LIMITED | BM3: 110100 | BO3: SOCIETE GENERALE GHANA LTD | BP3: 90100 | BR3: STANBIC BANK GHANA LIMITED | BS3: 190100 | BU3: STANDARD CHARTERED BANK (GHANA) LIMITED | BV3: 20100 | BX3: UNITED BANK FOR AFRICA (GHANA) LIMITED | BY3: 60100 | CA3: KANESHIE | CB3: 100105 | CD3: ZENITH BANK (GHANA) LIMITED | CE3: 120100 | CH3: Absa (GH) LTDBARCLAYS BANK OF GHANA LIMITED | CI3: 30100
A4: Access Bank (Ghana) Plc | C4: KASOA | D4: 30101 | F4: EAST CANTONMENTS BRANCH | G4: 280101 | I4: CONSUMER BANKING | J4: 80020 | L4: HEAD OFFICE-SOUTH RIDGE ACCRA | M4: 70101 | O4: FARRAR | P4: 210101 | R4: ACCRA | S4: 10101 | U4: ADABRAKA | V4: 270101 | X4: INDEPENDENCE AVENUE | Y4: 140101 | AA4: AIRPORT CITY BRANCH | AB4: 340101 | AD4: HEAD OFFICE | AE4: 130101 | AG4: MAKOLA | AH4: 200101 | AJ4: MULTICREDIT SAVINGS & LOANS LIMITED | AK4: 170650 | AM4: HEAD OFFICE | AN4: 170101 | AP4: FIRST NATIONAL BANK (GHANA) LIMITED | AQ4: 330100 | AS4: TUMU | AT4: 40002 | AV4: AIRPORT CITY BRANCH | AW4: 390101 | AZ4: HEAD OFFICE | BA4: 230101 | BC4: ACCRA MAIN | BD4: 50101 | BF4: HEAD OFFICE | BG4: 360101 | BI4: ACCRA | BJ4: 180101 | BL4: EBANKESE | BM4: 110101 | BO4: ACCRA MAIN | BP4: 90101 | BR4: ACCRA MAIN | BS4: 190101 | BU4: HIGH STREET | BV4: 20101 | BX4: HEAD OFFICE-RIDGE | BY4: 60101 | CA4: ABEKA BRANCH | CB4: 100106 | CD4: PREMIER TOWERS | CE4: 120101 | CH4: Absa (GH) LTDKASOA | CI4: 30101
A5: Agricultural Development Bank Limited | C5: A AND C MALL | D5: 30104 | F5: TEMA MAIN BRANCH | G5: 280102 | I5: PARASTATALS | J5: 80030 | L5: APEX BANKACCRA CENTRE-ACCRA | M5: 70102 | O5: RIDGE | P5: 210102 | R5: BANK OF GHANA WEST-TEST | S5: 10122 | U5: ACCRA CENTRAL | V5: 270102 | X5: TEMA | Y5: 140102 | AA5: RIDGE BRANCH | AB5: 340102 | AD5: TEMA | AE5: 130102 | AG5: KASOA | AH5: 200102 | AJ5: DORMAA CREDIT UNION | AK5: 240087 | AM5: KANTAMANTO AGENCY | AN5: 170102 | AP5: JUNCTION SHOPPING CENTRE | AQ5: 330101 | AS5: LAWRA | AT5: 40003 | AV5: TAKORADI BRANCH | AW5: 390401 | AZ5: AIRPORT | BA5: 230102 | BC5: TEMA MAIN | BD5: 50109 | BF5: ABOSSEY OKAI | BG5: 360102 | BI5: ABOSSEY OKAI | BJ5: 180102 | BL5: ACCRA CENTRAL | BM5: 110103 | BO5: NORTH INDUSTRIAL AREA | BP5: 90102 | BR5: AIRPORT CITY | BS5: 190102 | BU5: INDEPENDENCE AVENUE | BV5: 20102 | BX5: ACCRA CENTRAL | BY5: 60102 | CA5: NORTH INDUSTRIAL | CB5: 100107 | CD5: PATRICE LUMUMBA ROAD | CE5: 120102 | CH5: Absa (GH) LTDA AND C MALL | CI5: 30104
A6: Apex Bank GH Limited | C6: ACCRA MALL | D6: 30105 | F6: OSU OXFORD BRANCH | G6: 280103 | I6: AGRIC FINANCING | J6: 80040 | L6: NYAKROM RURAL BANK LTD-NYAKROM | M6: 70103 | O6: MAAMOBI | P6: 210103 | R6: AGONA SWEDRU | S6: 10303 | U6: SPINTEX | V6: 270103 | X6: DERBY AVENUE | Y6: 140103 | AA6: TUDU BRANCH | AB6: 340103 | AD6: RING ROAD CENTRAL | AE6: 130103 | AG6: TEMA | AH6: 200103 | AJ6: GOLDEN PRIDE SAVINGS & LOANS | AK6: 240091 | AM6: TEMA | AN6: 170103 | AP6: ACCRA | AQ6: 330102 | AS6: BOLE | AT6: 40004 | AV6: KUMASI BRANCH | AW6: 390601 | AZ6: TEMA | BA6: 230103 | BC6: OSU | BD6: 50111 | BF6: ASHAIMAN | BG6: 360103 | BI6: GICEL | BJ6: 180103 | BL6: RIDGE | BM6: 110104 | BO6: TUDU | BP6: 90103 | BR6: SPINTEX ROAD | BS6: 190103 | BU6: LIBERIA ROAD | BV6: 20104 | BX6: TEMA | BY6: 60103 | CA6: TEMA EAST | CB6: 100108 | CD6: TEMA COMMUNITY 1 | CE6: 120103 | CH6: Absa (GH) LTDACCRA MALL | CI6: 30105
A7: Bank of Africa Ghana Limited | C7: ABEKA LAPAZ | D7: 30106 | F7: LASHIBI BRANCH | G7: 280104 | I7: COMMERCIAL BANKING | J7: 80050 | L7: MANYA KROBO RURAL BANK LTD-ODUMASE-KROBO | M7: 70104 | O7: ACCRA CENTRAL | P7: 210104 | R7: TAKORADI | S7: 10401 | U7: NIMA | V7: 270104 | X7: SPINTEX ROAD | Y7: 140104 | AA7: TEMA COMMUNITY 1 BRANCH | AB7: 340104 | AD7: TUDU | AE7: 130104 | AG7: KANESHIE | AH7: 200104 | AJ7: SINAPI ABA SAVINGS & LOANS | AK7: 240092 | AM7: MAKOLA | AN7: 170104 | AP7: ACCRA MALL | AQ7: 330106 | AS7: GCB BANK LIMITED | AT7: 40100 | AZ7: OSU | BA7: 230104 | BC7: FOREIGN | BD7: 50112 | BF7: DZORWULU | BG7: 360104 | BI7: TEMA FISHING HABOUR | BJ7: 180104 | BL7: TEMA | BM7: 110105 | BO7: ACCRA NEW TOWN | BP7: 90104 | BR7: ACCRA MALL | BS7: 190104 | BU7: OPEIBEA HOUSE | BV7: 20105 | BX7: ABOSSEYOKAI | BY7: 60104 | CA7: ACHIMOTA | CB7: 100109 | CD7: KOJO THOMPSON ROAD BRANCH | CE7: 120104 | CH7: Absa (GH) LTDABEKA LAPAZ | CI7: 30106
A8: Bank of Ghana | C8: DANSOMAN | D8: 30107 | F8: OSU WATSON BRANCH | G8: 280105 | I8: AGRIC VALUE CHAIN | J8: 80060 | L8: GOMOA RURAL BANK LTD-APAM | M8: 70105 | O8: NEWTOWN | P8: 210105 | R8: SEFWI BOAKO | S8: 10402 | U8: NORTH INDUSTRIAL AREA | V8: 270105 | X8: GRAPHIC ROAD | Y8: 140105 | AA8: ACCRA CENTRAL BRANCH | AB8: 340105 | AD8: SILVER STAR | AE8: 130105 | AG8: RING ROAD CENTRAL | AH8: 200105 | AJ8: UTRAK SAVINGS AND LOANS | AK8: 240093 | AM8: NORTH RIDGE | AN8: 170105 | AP8: ACHIMOTA MALL | AQ8: 330107 | AS8: HIGH STREET | AT8: 40101 | AZ8: SPINTEX ROAD | BA8: 230105 | BC8: TEMA HABOUR AREA(AFKO) | BD8: 50113 | BF8: DOME | BG8: 360105 | BI8: MADINA | BJ8: 180105 | BL8: LEGON | BM8: 110107 | BO8: FAANOFA | BP8: 90105 | BR8: NORTH INDUSTIAL AREA | BS8: 190105 | BU8: TEMA | BV8: 20106 | BX8: RING ROAD | BY8: 60107 | CA8: ABOSEY OKAI | CB8: 100110 | CD8: SPINTEX | CE8: 120105 | CH8: Absa (GH) LTDDANSOMAN | CI8: 30107
A9: BSIC Ghana Limited | C9: GNPC | D9: 30108 | F9: KANTAMANTO BRANCH | G9: 280106 | I9: BUSINESS FINANCE | J9: 80070 | L9: ANUM RURAL BANK LTD-ANUM | M9: 70106 | O9: MICHEL CAMP | P9: 210106 | R9: KUMASI | S9: 10601 | U9: MADINA | V9: 270106 | X9: TEMA HARBOUR | Y9: 140106 | AA9: MAKOLA BRANCH | AB9: 340106 | AD9: OSU | AE9: 130106 | AG9: DANSOMAN | AH9: 200106 | AJ9: ABII NATIONAL SAVINGS AND LOANS LTD | AK9: 240094 | AM9: SPINTEX BRANCH | AN9: 170107 | AP9: WEST HILLS MALL | AQ9: 330108 | AS9: BURMA CAMP | AT9: 40102 | AZ9: LABONE | BA9: 230106 | BC9: LOTTERIES | BD9: 50116 | BF9: NMAI-DJORN | BG9: 360106 | BI9: MAKOLA | BJ9: 180107 | BL9: ABOSEY OKAI | BM9: 110108 | BO9: TEMA COMMUNITY TWO | BP9: 90106 | BR9: TEMA INDUSTRIAL AREA | BS9: 190106 | BU9: TUDU | BV9: 20107 | BX9: DZORWULU 1 MOTORWAY | BY9: 60108 | CA9: SOUTH INDUSTRIAL AREA | CB9: 100111 | CD9: GRAPHIC ROAD | CE9: 120106 | CH9: Absa (GH) LTDGNPC | CI9: 30108
A10: CAL Bank Limited | C10: NIMA | D10: 30109 | F10: KANESHIE BRANCH | G10: 280107 | I10: HEAD OFFICE | J10: 80100 | L10: AKUAPEM RURAL BANK LTD-MAMFE | M10: 70107 | O10: EAST LEGON | P10: 210111 | R10: SUNYANI | S10: 10701 | U10: TEMA | V10: 270107 | X10: WEIJA BRANCH | Y10: 140107 | AA10: ARENA BRANCH | AB10: 340107 | AD10: A AND C | AE10: 130107 | AG10: SPINTEX ROAD | AH10: 200107 | AJ10: BOND SAVINGS AND LOANS | AK10: 240095 | AM10: AIRPOT BRANCH | AN10: 170108 | AP10: MAKOLA | AQ10: 330111 | AS10: LEGON | AT10: 40103 | AZ10: GRAPHIC ROAD | BA10: 230107 | BC10: ABEKA | BD10: 50117 | BF10: TEMA 1 | BG10: 360107 | BI10: RING ROAD CENTRAL | BJ10: 180109 | BL10: TUDU | BM10: 110109 | BO10: OSU | BP10: 90107 | BR10: GRAPHIC ROAD | BS10: 190107 | BU10: LEGON | BV10: 20108 | BX10: DZORWULU 2 | BY10: 60109 | CA10: OSU | CB10: 100112 | CD10: NORTH INDUSTRIAL AREA | CE10: 120107 | CH10: Absa (GH) LTDNIMA | CI10: 30109
A11: Consolidated Bank Ghana Limited | C11: LEGON | D11: 30110 | F11: CASTLE ROAD BRANCH | G11: 280108 | I11: RING ROAD CENTRAL | J11: 80101 | L11: DANGBE RURAL BANK LTD-PRAMPRAM | M11: 70108 | O11: KWASHIEMAN | P11: 210112 | R11: TAMALE | S11: 10801 | U11: DARKUMAN | V11: 270108 | X11: CIRCLE BRANCH | Y11: 140108 | AA11: KOKOMLEMLE | AB11: 340108 | AD11: TEMA LONG ROOM | AE11: 130108 | AG11: SWEDRU | AH11: 200108 | AJ11: PAY HUB | AK11: 240096 | AM11: ABOSSEY OKAI BRANCH | AN11: 170109 | AP11: TEMA | AQ11: 330112 | AS11: MINISTRIES | AT11: 40105 | AZ11: ASHIAMAN | BA11: 230108 | BC11: CLEARING UNIT | BD11: 50120 | BF11: KOKOMLEMLE | BG11: 360108 | BI11: SPINTEX ROAD | BJ11: 180110 | BL11: AGBOGBLOSHIE | BM11: 110112 | BO11: OKAISHIE | BP11: 90108 | BR11: MAKOLA | BS11: 190108 | BU11: OSU | BV11: 20112 | BX11: MADINA | BY11: 60110 | CA11: JUNCTION MALL BRANCH | CB11: 100115 | CD11: LABONE | CE11: 120108 | CH11: Absa (GH) LTDLEGON | CI11: 30110
A12: Ecobank Ghana Limited | C12: ACHIMOTA | D12: 30111 | F12: ACCESS BANK -MADINA BRANCH | G12: 280109 | I12: ADABRAKA | J12: 80102 | L12: SHAI RURAL BANK LTD-DODOWA | M12: 70109 | O12: OSU | P12: 210113 | R12: HOHOE | S12: 11101 | U12: ACHIMOTA | V12: 270109 | X12: LEGON | Y12: 140109 | AA12: ACHITOMA BRANCH | AB12: 340109 | AD12: MCCARTHY HILL | AE12: 130109 | AG12: ACHIMOTA | AH12: 200109 | AJ12: PROCREDIT SAVINGS AND LOANS COMPANY LTD | AK12: 240097 | AM12: NORTH INDUSTRIAL AREA | AN12: 170110 | AS12: REPUBLIC HOUSE | AT12: 40106 | AZ12: TUDU | BA12: 230109 | BC12: ADENTA | BD12: 50122 | BF12: MADINA | BG12: 360109 | BI12: TEMA COMMUNITY 1 | BJ12: 180111 | BL12: BAATSONA | BM12: 110116 | BO12: KANASHIE | BP12: 90109 | BR12: RIND ROAD | BS12: 190109 | BU12: SPINTEX | BV12: 20118 | BX12: EAST LEGON 1 | BY12: 60111 | CA12: UNIVERSAL EAST LEGON BRANCH | CB12: 100116 | CD12: EAST LEGON | CE12: 120109 | CH12: Absa (GH) LTDACHIMOTA | CI12: 30111
A13: FBN Bank (Ghana) Limited | C13: OSU | D13: 30112 | F13: SOUTH INDUSTRIAL BRANCH | G13: 280110 | I13: TEMA | J13: 80103 | L13: ADA RURAL BANK LTD-KASSEH | M13: 70110 | O13: SPINTEX ROAD | P13: 210114 | U13: TAKORADI | V13: 270401 | X13: RING ROAD CENTRAL | Y13: 140110 | AA13: ADABRAKA BRANCH | AB13: 340110 | AD13: ROMAN RIDGE BRANCH | AE13: 130110 | AG13: SWANMILL | AH13: 200110 | AJ13: ALPHA CAPITAL SAVING&L LTD | AK13: 240098 | AM13: OSU OXFORD STREET BRANCH | AN13: 170111 | AS13: TEMA MAIN | AT13: 40107 | AZ13: MADINA | BA13: 230110 | BC13: SPINTEX | BD13: 50123 | BF13: TUDU | BG13: 360110 | BI13: WEIJA | BJ13: 180112 | BL13: PRIVATE BANKING | BM13: 110117 | BO13: TEMA FISHING HARBOUR | BP13: 90110 | BR13: ACHIMOTA | BS13: 190110 | BU13: DANSOMAN | BV13: 20121 | BX13: EAST LEGON 2 | BY13: 60112 | CA13: OXFORD STREET | CB13: 100117 | CD13: TEMA INDUSTRIAL AREA | CE13: 120110 | CH13: Absa (GH) LTDOSU | CI13: 30112
A14: Fidelity Bank Limited | C14: RING ROAD CENTRAL | D14: 30114 | F14: NIA BRANCH | G14: 280111 | I14: TESHIE | J14: 80104 | L14: BRAKWA BRAMAN RURAL BANK LTD-BRAKWA | M14: 70111 | O14: TEMA | P14: 210116 | U14: KUMASI | V14: 270601 | X14: ACHIMOTA | Y14: 140111 | AA14: ADENTA BRANCH | AB14: 340111 | AD14: ABEKA LAPAZ | AE14: 130111 | AG14: KORLE-BU | AH14: 200111 | AJ14: SOVEREIGN BANK LIMITED | AK14: 240099 | AM14: WEIJA BRANCH | AN14: 170113 | AS14: TEMA MARKET | AT14: 40108 | AZ14: ACHIMOTA | BA14: 230111 | BC14: WINNEBA ROAD | BD14: 50124 | BF14: SPINTEX | BG14: 360111 | BI14: TESANO | BJ14: 180113 | BL14: ASHIAMAN | BM14: 110118 | BO14: KOTOBABI | BP14: 90111 | BR14: ROMAN RIDGE | BS14: 190111 | BU14: ABEKA | BV14: 20126 | BX14: TESHIE | BY14: 60113 | CA14: SPINTEX ROAD | CB14: 100118 | CD14: ACHIMOTA BRANCH | CE14: 120111 | CH14: Absa (GH) LTDRING ROAD CENTRAL | CI14: 30114
A15: First Atlantic Bank Limited | C15: BCM | D15: 30116 | F15: RING ROAD CENTRAL BRANCH | G15: 280112 | I15: KANESSHIE | J15: 80105 | L15: EASTERN GOMOA ASSIN RURAL BANK LTD-GOMOA-DOMINASE | M15: 70112 | O15: DANSOMAN | P15: 210117 | U15: KUMASI (ALABAR) | V15: 270602 | X15: OSU | Y15: 140112 | AA15: SPINTEX BRANCH | AB15: 340112 | AD15: DANSOMAN | AE15: 130112 | AG15: DOME | AH15: 200112 | AJ15: HEAD OFFICE | AK15: 240100 | AM15: EAST LEGON MAIN BRANCH | AN15: 170114 | AS15: TEMA INDUSTRIAL AREA | AT15: 40109 | AZ15: NIA | BA15: 230112 | BC15: NORTH INDUSTRIAL AREA | BD15: 50128 | BF15: OSU | BG15: 360112 | BI15: ZONGO JUNCTION | BJ15: 180114 | BL15: POST OFFICE SQUARE | BM15: 110119 | BO15: PREMIER TOWERS | BP15: 90114 | BR15: KASOA | BS15: 190112 | BU15: ACHIMOTA | BV15: 20127 | BX15: SPINTEX ROAD | BY15: 60114 | CA15: MADINA | CB15: 100122 | CD15: AKOSOMBO BRANCH | CE15: 120112 | CH15: Absa (GH) LTDBCM | CI15: 30116
A16: First National Bank (Ghana) Limited | C16: MOTORWAY EXT | D16: 30117 | F16: KANESHIE POST OFFICE BRANCH | G16: 280113 | I16: CEDI HOUSE | J16: 80106 | L16: GOMOA AJUMAKO RURAL BANK LTD-AFRANSI | M16: 70113 | O16: MADINA | P16: 210118 | U16: TAMALE | V16: 270801 | X16: COMMUNITY 25 | Y16: 140113 | AA16: AMERICAN HOUSE BRANCH | AB16: 340113 | AD16: TEMA COMMUNITY 6 | AE16: 130113 | AG16: SANTA MARIA | AH16: 200113 | AJ16: RIDGE TOWERS | AK16: 240101 | AM16: KOTOBABI BRANCH | AN16: 170115 | AS16: TEMA FISHING HARBOUR | AT16: 40110 | AZ16: COMMUNITY 6 | BA16: 230113 | BC16: TEMA COMMUNITY 9 | BD16: 50129 | BF16: WEIJA | BG16: 360113 | BI16: ODORKOR | BJ16: 180115 | BL16: ADABRAKA BRANCH | BM16: 110120 | BO16: HEAD OFFICE | BP16: 90115 | BR16: TEMA FISHING HABOUR | BS16: 190113 | BU16: NIA | BV16: 20129 | BX16: NORTH INDUSTRIAL AREA BUSINESS OFFICE | BY16: 60127 | CA16: BAYPORT SAVINGS & LOANS LTD | CB16: 100138 | CD16: TEMA METRO BRANCH | CE16: 120113 | CH16: Absa (GH) LTDMOTORWAY EXT | CI16: 30117
A17: GCB Bank Limited | C17: SPINTEX MAIN | D17: 30121 | F17: ABEKA LAPAZ BRANCH | G17: 280114 | I17: ADB -INTERNATIONAL BANKING | J17: 80107 | L17: AGONA RURAL BANK LTD-KWANYAKU | M17: 70114 | O17: ABOSSEY OKAI | P17: 210119 | X17: EAST LEGON BRANCH | Y17: 140114 | AA17: ANYAA BRANCH | AB17: 340114 | AD17: DARKUMAN | AE17: 130114 | AG17: SPINTEX 2 BRANCH | AH17: 200114 | AJ17: SPINTEX ROAD | AK17: 240102 | AM17: SAKUMONO BRANCH | AN17: 170116 | AS17: RING ROAD WEST | AT17: 40111 | AZ17: OPERA SQUARE | BA17: 230114 | BC17: HEAD OFFICE | BD17: 50131 | BF17: EAST LEGON | BG17: 360114 | BI17: ABEKA | BJ17: 180116 | BL17: DANSOMAN BRANCH | BM17: 110121 | BO17: SPINTEX ROAD | BP17: 90117 | BR17: MOVENPICK | BS17: 190114 | BU17: WESTLANDS | BV17: 20131 | BX17: ACHIMOTA | BY17: 60129 | CA17: NDK FINANCIAL SERVICES | CB17: 100140 | CD17: FREE ZONES BRANCH | CE17: 120114 | CH17: Absa (GH) LTDSPINTEX MAIN | CI17: 30121
A18: GHL Bank Limited | C18: KNUTSFORD AVENUE | D18: 30122 | F18: OKAISHIE BRANCH | G18: 280115 | I18: GULF HOUSE | J18: 80108 | L18: AKYEPIM RURAL BANK LTD-GOMOA-DAW | M18: 70115 | O18: TAKORADI | P18: 210401 | X18: DANSOMAN | Y18: 140115 | AA18: APENKWA BRANCH | AB18: 340115 | AD18: LEGON | AE18: 130115 | AG18: AIRPORT BRANCH | AH18: 200115 | AJ18: HIGH STREET | AK18: 240103 | AM18: SAKAMAN | AN18: 170119 | AS18: KANESHIE MARKET | AT18: 40112 | AZ18: LAPAZ | BA18: 230115 | BC18: DANSOMAN | BD18: 50132 | BF18: TEMA 2 | BG18: 360115 | BI18: NORTH INDUSTRIAL AREA | BJ18: 180117 | BL18: ACCRA NEW TOWN | BM18: 110122 | BO18: MADINA | BP18: 90118 | BR18: MADINA | BS18: 190115 | BU18: TEMA HABOUR | BV18: 20132 | BX18: THE SEED SAVINGS AND LOANS | BY18: 60150 | CA18: INNOVATION AGAINST POVERTY | CB18: 100141 | CD18: TRADE FAIR BRANCH | CE18: 120115 | CH18: Absa (GH) LTDKNUTSFORD AVENUE | CI18: 30122
A19: Guaranty Trust Bank (Ghana) Limited | C19: LEGON MAIN | D19: 30125 | F19: ASHAIMAN BRANCH | G19: 280116 | I19: DANSOMAN | J19: 80109 | L19: AWUTU EMASA RURAL BANK LTD-AWUMASA | M19: 70116 | O19: KUMASI AMAKOM | P19: 210601 | X19: LABONE | Y19: 140116 | AA19: ASHAIMAN ROUND ABOUT | AB19: 340116 | AD19: SOUTH INDUSTRIAL AREA(SIA) | AE19: 130116 | AG19: TAKORADI | AH19: 200401 | AJ19: OSU | AK19: 240104 | AM19: DWORWULU | AN19: 170120 | AS19: KORLEBU | AT19: 40113 | AZ19: EAST LEGON | BA19: 230116 | BC19: ASHAIMAN BRANCH | BD19: 50134 | BF19: KOFORIDUA | BG19: 360201 | BI19: ADENTA | BJ19: 180118 | BL19: MADINA | BM19: 110123 | BO19: KASOA | BP19: 90119 | BR19: DANSOMAN | BS19: 190116 | BU19: WESTHILLS | BV19: 20133 | BX19: GOLDEN LINK SAVINGS & LOANS | BY19: 60170 | CA19: INTERNATIONAL NEEDS LIMITED | CB19: 100142 | CD19: SAKAMAN BRANCH | CE19: 120116 | CH19: Absa (GH) LTDLEGON MAIN | CI19: 30125
A20: National Investment Bank Limited | C20: TEMA FISHING HARBOUR | D20: 30130 | F20: IPS BRANCH | G20: 280117 | I20: NUNGUA | J20: 80110 | L20: GA RURAL BANK LTD-AMASAMAN | M20: 70117 | O20: KUMASI -ADUM | P20: 210602 | X20: AIRPORT CITY BRANCH | Y20: 140117 | AA20: ASHAIMAN MAIN BRANCH | AB20: 340117 | AD20: SPINTEX | AE20: 130117 | AG20: ADUM | AH20: 200601 | AJ20: ABOSSEY OKAI | AK20: 240105 | AM20: RING ROAD | AN20: 170121 | AS20: OSU | AT20: 40114 | AZ20: DOME | BA20: 230117 | BC20: AIRPORT CITY | BD20: 50135 | BF20: KASOA | BG20: 360301 | BI20: KWAME NKRUMAH CIRCLE | BJ20: 180119 | BL20: ACHIMOTA | BM20: 110124 | BO20: TEMA COMMUNITY ONE | BP20: 90120 | BR20: ASHAIMAN | BS20: 190117 | BU20: LIBERIA ROAD TAKORADI | BV20: 20436 | BX20: TAKORADI | BY20: 60402 | CA20: SAHAM LIFE LIMITED | CB20: 100143 | CD20: PREMIER TOWERS BRANCH | CE20: 120117 | CH20: Absa (GH) LTDTEMA FISHING HARBOUR | CI20: 30130
A21: Omni Bank Ghana Limited | C21: MAKOLA SQUARE | D21: 30135 | F21: ACHIMOTA BRANCH | G21: 280118 | I21: KORKORDZOR | J21: 80111 | L21: ABOKOBI RURAL BANK LTD-ABOKOBI | M21: 70118 | O21: SOKOBAN | P21: 210603 | X21: AIRPORT REFINERY | Y21: 140118 | AA21: ASHALLEY BOTWE BRANCH | AB21: 340118 | AD21: ACCRA SHOPPING MALL | AE21: 130118 | AG21: SUAME | AH21: 200602 | AJ21: TEMA SAFE BOND | AK21: 240106 | AM21: MADINA | AN21: 170122 | AS21: DERBY AVENUE | AT21: 40115 | AZ21: MAKOLA | BA21: 230118 | BC21: EAST LEGON | BD21: 50136 | BF21: TAKORADI | BG21: 360401 | BI21: MATAHEKO | BJ21: 180120 | BL21: LEGON ANNEX BRANCH | BM21: 110125 | BO21: ASHAIMAN | BP21: 90121 | BR21: TEMA COMMUNITY ONE | BS21: 190118 | BU21: KNUST | BV21: 20611 | BX21: TARKWA | BY21: 60403 | CA21: VANGUARD ASSURANCE | CB21: 100144 | CD21: KOFORIDUA BRANCH | CE21: 120201 | CH21: Absa (GH) LTDMAKOLA SQUARE | CI21: 30135
A22: Prudential Bank Limited | C22: AIRPORT CITY | D22: 30136 | F22: TEMA COMMUNITY 1 BRANCH | G22: 280119 | I22: OSU | J22: 80112 | L22: BAWJIASE AREA RURAL BANK LTD-AWUTU BAWJIASE | M22: 70119 | O22: MULTICREDIT SAVINGS AND LOANS CO. | P22: 210699 | X22: EMAN CAPITAL MICROFINANCE LTD | Y22: 140189 | AA22: ASHIYE BRANCH | AB22: 340119 | AD22: TEMA SHOPPING MALL | AE22: 130119 | AG22: TECHIMAN | AH22: 200701 | AJ22: KANTAMANTO | AK22: 240107 | AM22: OSU MEDIUM | AN22: 170125 | AS22: BOUNDARY ROAD | AT22: 40116 | AZ22: RING ROAD BRANCH | BA22: 230119 | BC22: LAW COURT COMPLEX BRANCH | BD22: 50138 | BF22: TARKWA | BG22: 360402 | BI22: OKAISHIE | BJ22: 180121 | BL22: ADJIRIGANO BRANCH | BM22: 110126 | BO22: EAST LEGON BRANCH | BP22: 90122 | BR22: EAST LEGON | BS22: 190119 | BU22: AHODWO | BV22: 20613 | BX22: KUMASI-ADUM | BY22: 60601 | CA22: IFS CAPITAL MANAGEMENT | CB22: 100145 | CD22: CAPE COAST BRANCH | CE22: 120301 | CH22: Absa (GH) LTDAIRPORT CITY | CI22: 30136
A23: Republic Bank (Ghana) Limited | C23: CIRCLE | D23: 30141 | F23: NIMA BRANCH | G23: 280120 | I23: MADINA | J23: 80113 | L23: AGAVE RURAL BANK LTD-DABALE | M23: 70120 | O23: TAMALE | P23: 210801 | X23: PRIVATE BANKING | Y23: 140190 | AA23: ATOMIC JUNCTION BRANCH | AB23: 340120 | AD23: WEIJA | AE23: 130120 | AJ23: TUDU | AK23: 240108 | AM23: TEMA COMM1 | AN23: 170126 | AS23: LIBERTY HOUSE | AT23: 40117 | AZ23: BAATSONA BRANCH | BA23: 230120 | BC23: PARLIAMENT HOUSE BRANCH | BD23: 50139 | BF23: MANHYIA | BG23: 360601 | BI23: EAST LEGON BRANCH | BJ23: 180122 | BL23: COMMUNITY 25 | BM23: 110127 | BO23: AIRPORT CITY BRANCH | BP23: 90123 | BR23: LAPAZ | BS23: 190120 | BU23: HARPER ROAD | BV23: 20615 | BX23: GOLDEN LINK S&L | BY23: 60620 | CA23: ENTERPRISE LIFE ASSURANCE | CB23: 100146 | CD23: TAKORADI MAIN | CE23: 120401 | CH23: Absa (GH) LTDCIRCLE | CI23: 30141
A24: Societe General (Ghana) Limited | C24: ACCRA CORPORATE SERVICE CENTRE | D24: 30144 | F24: TIA BRANCH | G24: 280121 | I24: ABEKALAPAZ | J24: 80114 | L24: MEPE AREA RURAL BANK LTD-MEPE | M24: 70121 | O24: ABII NATIONAL SAVINGS AND LOANS | P24: 210900 | X24: SUAME CIRCUIT CO-OPERATIVE CREDIT U | Y24: 140194 | AA24: DANSOMAN ROUND-ABOUT BRANCH | AB24: 340122 | AD24: ACHIMOTA MILE 7 | AE24: 130121 | AJ24: TEMA-COMMUNITY ONE | AK24: 240109 | AM24: SPINTEX BRANCH 2 | AN24: 170127 | AS24: ACCRA NEW TOWN | AT24: 40118 | AZ24: TEMA MAIN HARBOUR BRANCH | BA24: 230122 | BC24: MADINA BRANCH | BD24: 50146 | BF24: KUMASI CENTRAL MARKET | BG24: 360602 | BI24: BAWALESHIE BRANCH | BJ24: 180123 | BL24: ANT-MIDLAND SAVINGS AND LOANS | BM24: 110128 | BO24: DANSOMAN BRANCH | BP24: 90124 | BR24: STANBIC HEIGHTS | BS24: 190121 | BU24: OBUASI | BV24: 20617 | BX24: TAMALE | BY24: 60801 | CA24: EZI SAVINGS AND LOANS LTD | CB24: 100148 | CD24: TAKORADI HABOUR BRANCH | CE24: 120402 | CH24: Absa (GH) LTDACCRA CORPORATE SERVICE CENTRE | CI24: 30144
A25: Stanbic Bank Ghana Limited | C25: SPINTEX PRESTIGE | D25: 30145 | F25: AIRPORT BRANCH | G25: 280122 | I25: AGONA SWEDRU | J25: 80115 | L25: UNION RURAL BANK LTD-SENYA BREKU | M25: 70122 | O25: ECLIPSE MICROFINANCE | P25: 210910 | X25: JAUBEN RURAL BANK LTD | Y25: 140195 | AA25: DANSOMAN EXHIBITION BRANCH | AB25: 340123 | AD25: MADINA | AE25: 130122 | AJ25: OKAISHIE | AK25: 240110 | AM25: 37 BRANCH | AN25: 170128 | AS25: TRADE FAIR SITE | AT25: 40119 | AZ25: ONE AIRPORT SQUARE | BA25: 230123 | BC25: MAKOLA | BD25: 50147 | BF25: KEJETIA | BG25: 360603 | BI25: NUNGUA BRANCH | BJ25: 180124 | BL25: ANT-ASSURANCE S AND L | BM25: 110129 | BO25: KOFORIDUA | BP25: 90201 | BR25: INTEGRATED PROCESSING CENTER | BS25: 190122 | BU25: TAMALE | BV25: 20823 | BX25: MERCHANT BANK | BY25: 100100 | CA25: PACIFIC SAVINGS AND LOANS LTD | CB25: 100149 | CD25: TARKWA | CE25: 120403 | CH25: Absa (GH) LTDSPINTEX PRESTIGE | CI25: 30145
A26: Standard Chartered Bank (Ghana) Limited | C26: HIGH STREET | D26: 30148 | F26: KASOA BRANCH | G26: 280123 | I26: ADB HOUSE BRANCH | J26: 80116 | L26: ANLO RURAL BANK LTD-ANLOGA | M26: 70123 | O26: GOLDMAN CAPITAL | P26: 210920 | X26: ODOTOBRI RURAL BANK LTD | Y26: 140196 | AA26: RUSSIA ROAD BRANCH | AB26: 340124 | AD26: HAATSOO | AE26: 130123 | AJ26: ACTION CHAPEL | AK26: 240111 | AM26: TRADE FAIR | AN26: 170129 | AS26: KANESHIE INDUSTRIAL AREA | AT26: 40120 | AZ26: DANSOMAN | BA26: 230124 | BC26: ACCRA NEW TOWN | BD26: 50149 | BF26: ANLOGA | BG26: 360604 | BI26: VALLEY VIEW UNIVERSITY BRANCH | BJ26: 180125 | BL26: UG CO-OPERATIVE CREDIT UNION | BM26: 110130 | BO26: AKIM ODA | BP26: 90202 | BR26: CASH CENTRE | BS26: 190123 | CA26: CDH BALANCED FUND | CB26: 100175 | CD26: KUMASI MAIN | CE26: 120601 | CH26: Absa (GH) LTDHIGH STREET | CI26: 30148
A27: United Bank for Africa (Ghana) Limited | C27: DIRECT SALES | D27: 30149 | F27: SPINTEX BRANCH | G27: 280124 | I27: ACHIMOTA | J27: 80117 | L27: ODUPONGKPEHE RURAL BANK LTD-KASOA | M27: 70124 | O27: MIDLAND SAVINGS AND LOANS | P27: 210930 | X27: MIDLAND SAVINGS & LOANS LTD | Y27: 140197 | AA27: DARKUMAN BRANCH | AB27: 340125 | AD27: WESTLANDS | AE27: 130124 | AJ27: A AND C MALL | AK27: 240112 | AM27: FIRST AFRICAN SAVINGS AND LOANS | AN27: 170174 | AS27: ASHAIMAN | AT27: 40121 | AZ27: GLOBAL ACCESS SAVINGS & LOANS CO. LTD | BA27: 230181 | BC27: FIRST GHANA BUILDING SOCIETY-HEAD OFFICE | BD27: 50150 | BF27: KRONUM | BG27: 360605 | BI27: UNIVERSITY OF GHANA BRANCH | BJ27: 180126 | BL27: KOFORIDUA | BM27: 110215 | BO27: CAPE COAST | BP27: 90301 | BR27: WEST HILLS MALL BRANCH | BS27: 190124 | CA27: STALWARD ASSETS COMPANY LIMITED | CB27: 100182 | CD27: ADUM | CE27: 120602 | CH27: Absa (GH) LTDDIRECT SALES | CI27: 30149
A28: Universal Merchant Bank Limited | C28: AVENUE CENTRAL | D28: 30154 | F28: NEWTOWN BRANCH | G28: 280125 | I28: SPINTEX ROAD | J28: 80118 | L28: LA COMMUNITY BANK LTD-LA | M28: 70125 | O28: GHANA HOME LOANS | P28: 210940 | X28: FIRST AFRICAN SAVINGS & LOANS LTD | Y28: 140198 | AA28: DOME BRANCH | AB28: 340126 | AD28: MOTOR WAY ROUNDABOUT | AE28: 130125 | AJ28: DANSOMAN | AK28: 240113 | AM28: UNION SAVINGS AND LOANS LIMITED | AN28: 170175 | AS28: MADINA | AT28: 40123 | AZ28: ASURANCE SAVINGS AND LOANS LTD | BA28: 230184 | BC28: FIRST GHANA BUILDING SOCIETY- ACCRA | BD28: 50151 | BF28: ADUM | BG28: 360606 | BI28: TAIFA BRANCH | BJ28: 180127 | BL28: ASAMANKESE | BM28: 110216 | BO28: DUNKWA | BP28: 90302 | BR28: JUNCTION MALL BRANCH | BS28: 190125 | CA28: GEMINI LIFE INSURANCE COMPANY | CB28: 100183 | CD28: SUAME BRANCH | CE28: 120603 | CH28: Absa (GH) LTDAVENUE CENTRAL | CI28: 30154
A29: Zenith Bank (Ghana) Limited | C29: UNDP | D29: 30155 | F29: HAATSO | G29: 280126 | I29: MAKOLA | J29: 80119 | L29: APEX LINK CENTRE-CEDI HOUSECED HOUSE | M29: 70126 | O29: HIS MAJESTY PHONES | P29: 210950 | X29: OPPORTUNITY SAVINGS & LOANS | Y29: 140199 | AA29: DZORWULU BRANCH | AB29: 340127 | AD29: KOTOBABI | AE29: 130127 | AJ29: RING ROAD | AK29: 240114 | AM29: ENTREPRENUERS CAPITAL CO-OPERATIVE CREDIT UNION | AN29: 170176 | AS29: 31ST DECEMBER MARKET | AT29: 40124 | AZ29: CAPE - COAST BRANCH | BA29: 230301 | BC29: ACHIMOTA BRANCH | BD29: 50152 | BI29: GOLDEN LINK SAVINGS AND LOANS | BJ29: 180199 | BL29: KASOA BRANCH | BM29: 110301 | BO29: TAKORADI | BP29: 90401 | BR29: TUDU BRANCH | BS29: 190127 | CA29: EXPRESS SAVINGS AND LOANS LTD | CB29: 100184 | CD29: SUNYANI | CE29: 120701 | CH29: Absa (GH) LTDUNDP | CI29: 30155
C30: TEMA MAIN | D30: 30160 | F30: AIRPORT | G30: 280127 | I30: ACCRA NEW TOWN | J30: 80120 | L30: ASUOGYAMAN RURAL BANK LTD-ACCRA | M30: 70127 | O30: CIMENTS DE L'AFRIQUE | P30: 210960 | X30: TAKORADI | Y30: 140401 | AA30: EAST LEGON BRANCH | AB30: 340128 | AD30: SAFE BOND | AE30: 130128 | AJ30: HAATSO | AK30: 240115 | AM30: ASI-B SAVINGS AND LOANS | AN30: 170177 | AS30: TETTEH QUARSHIE CIRCLE | AT30: 40126 | AZ30: KASOA BRANCH | BA30: 230302 | BC30: EAST AIRPORT BRANCH | BD30: 50153 | BI30: KOFORIDUA | BJ30: 180201 | BL30: SWEDRU | BM30: 110302 | BO30: SEFWI BEKWAI | BP30: 90402 | BR30: ACHIMOTA MALL BRANCH | BS30: 190128 | CA30: UNIVERSAL PRIVATE BANKING BRANCH | CB30: 100190 | CD30: TAMALE | CE30: 120801 | CH30: Absa (GH) LTDTEMA MAIN | CI30: 30160
C31: SME CENTRE | D31: 30161 | F31: LEGON ACCRA | G31: 280128 | I31: TEMA MERIDIAN | J31: 80121 | L31: CITIZEN RURAL BANK LTD-ACCRA | M31: 70128 | O31: TEMA CHAPTERS TEACHERS NETWORK | P31: 210970 | X31: TARKWA | Y31: 140402 | AA31: GIMPA BRANCH | AB31: 340129 | AD31: LABONE | AE31: 130129 | AJ31: TEMA COMMUNITY 2 | AK31: 240116 | AM31: FAMB -ADOM SAVINGS & LOANS | AN31: 170179 | AS31: KWAME NKRUMAH CIRCLE | AT31: 40127 | AZ31: TAKORADI | BA31: 230401 | BC31: KISSEMAN BRANCH | BD31: 50154 | BI31: CAPECOAST BRANCH | BJ31: 180301 | BL31: CAPE COAST | BM31: 110303 | BO31: SEFWI WIAWSO | BP31: 90403 | BR31: LEGON | BS31: 190130 | CA31: SIC LIFE SAVINGS & LOANS LIMITED | CB31: 100197 | CH31: Absa (GH) LTDSME CENTRE | CI31: 30161
C32: AGBOBLOSHIE | D32: 30162 | F32: ADJIRIGANOR, ACCRA | G32: 280129 | I32: ASHIAMAN | J32: 80124 | L32: OYIBI AREA RURAL BANK LIMITED | M32: 70129 | X32: TAKORADI HARBOUR | Y32: 140403 | AA32: KANESHIE BRANCH | AB32: 340130 | AD32: BURMA CAMP | AE32: 130130 | AJ32: ACCRA CENTRAL POSTBANK | AK32: 240117 | AM32: SIC LIFE SAVINGS AND LOANS LIMITED | AN32: 170180 | AS32: INTERNATIONAL TRADE FINANCE | AT32: 40128 | AZ32: TARKWA | BA32: 230402 | BC32: TESHIE NUNGUA BRANCH | BD32: 50155 | BI32: UNIV. OF CAPE COAST BRANCH | BJ32: 180302 | BL32: WINNEBA | BM32: 110304 | BO32: TARKWA | BP32: 90404 | BR32: ALPHA CAPITAL SAVINGS AND LOANS | BS32: 190131 | CA32: IVORY FINANCE SAVINGS AND LOANS | CB32: 100198 | CH32: Absa (GH) LTDAGBOBLOSHIE | CI32: 30162
C33: MADINA | D33: 30163 | F33: ACCESS -OCTAGON ACCRA | G33: 280130 | I33: DANQUAH CIRCLE | J33: 80125 | L33: MICROFIN RURAL BANK LIMITED | M33: 70130 | X33: ESIAMA BRANCH | Y33: 140404 | AA33: KASOA MAIN BRANCH | AB33: 340131 | AD33: REINSURANCE HOUSE BRANCH | AE33: 130131 | AJ33: ADENTA | AK33: 240118 | AM33: UNICREDIT GHANA LIMITED | AN33: 170181 | AS33: GLOBAL TRANSFER SERVICES | AT33: 40129 | AZ33: AFLAO | BA33: 230501 | BC33: FIRST GHANA BUILDING SOCIETY-TEMA | BD33: 50159 | BI33: TAKORADI HARBOUR | BJ33: 180401 | BL33: TAKORADI | BM33: 110401 | BO33: ESSAM | BP33: 90405 | BR33: SERVICES INTERGRITY SAVINGS AND LOANS LIMITED | BS33: 190132 | CA33: FIRST NATATIONAL S&L | CB33: 100199 | CH33: Absa (GH) LTDMADINA | CI33: 30163
C34: HEAD OFFICE | D34: 30164 | F34: BESTPOINT SAVING & LOANS - ACCRA BANK | G34: 280162 | I34: NIMA | J34: 80126 | L34: GOMOA COMMUNITY BANK | M34: 70131 | X34: SEKONDI ROAD | Y34: 140405 | AA34: KASOA NEW MARKET | AB34: 340132 | AD34: TRUST TOWERS BRANCH | AE34: 130132 | AJ34: IPS | AK34: 240119 | AM34: TADI MARKT CIRCLE | AN34: 170401 | AS34: TANTRA HILL | AT34: 40130 | AZ34: KUMASI-LAKE ROAD | BA34: 230601 | BC34: KOFORIDUA | BD34: 50204 | BI34: TAKORADI MARKET CIRCLE | BJ34: 180402 | BL34: SEFWI WIAWSO | BM34: 110402 | BO34: ASANKRAGUA | BP34: 90406 | BR34: AGJIRINGANOR | BS34: 190133 | CA34: ICGC CHRIST TEMPLE | CB34: 100200 | CH34: Absa (GH) LTDHEAD OFFICE | CI34: 30164
C35: TESHIE NUNGUA | D35: 30168 | F35: FIRST TRUST SAVINGS AND LOANS LTD | G35: 280189 | I35: KASOA | J35: 80127 | L35: APEX BANK KOFORIDUA CENTRE-KOFORIDUA | M35: 70201 | X35: NHYIEASO | Y35: 140601 | AA35: KORLE BU BRANCH | AB35: 340133 | AD35: TESANO BRANCH | AE35: 130133 | AJ35: TRADE FAIR LA | AK35: 240120 | AM35: KUMASI | AN35: 170601 | AS35: KASOA | AT35: 40131 | AZ35: ADUM | BA35: 230602 | BC35: AKIM ODA | BD35: 50218 | BI35: KUMASI | BJ35: 180601 | BL35: SEFWI BEKWAI | BM35: 110403 | BO35: AKONTOMBRA | BP35: 90407 | BR35: TAKORADI | BS35: 190401 | CA35: FIRST INSURANCE CO. LTD | CB35: 100202 | CH35: Absa (GH) LTDTESHIE NUNGUA | CI35: 30168
C36: ACCRA NEWTOWN | D36: 30169 | F36: FASL | G36: 280198 | I36: WINNEBA | J36: 80128 | L36: ASUOPRA RURAL BANK LTD-AFOSU | M36: 70202 | X36: SUAME | Y36: 140602 | AA36: KORLE DUDOR BRANCH | AB36: 340134 | AD36: HOSPITAL ROAD BRANCH | AE36: 130134 | AJ36: TESANO | AK36: 240121 | AM36: SUAME | AN36: 170602 | AS36: DOME (KWABENYA) | AT36: 40132 | AZ36: ALABAR BRANCH | BA36: 230603 | BC36: FIRST GHANA BUILDING SOCIETY- KOFORIDUA | BD36: 50252 | BI36: ADUM-KUMASI | BJ36: 180602 | BL36: JUABESO | BM36: 110404 | BO36: JUABESO | BP36: 90408 | BR36: TARKWA | BS36: 190402 | CA36: BEIGE CAPITAL SAVINGS & LOANS | CB36: 100203 | CH36: Absa (GH) LTDACCRA NEWTOWN | CI36: 30169
C37: DOME | D37: 30170 | F37: KOFORIDUA | G37: 280201 | I37: DIAMOND CEMENT | J37: 80129 | L37: KWAHU RURAL BANK LTD-KWAHU PEPEASE | M37: 70203 | X37: KEJETIA | Y37: 140603 | AA37: KWABENYA BRANCH | AB37: 340135 | AD37: KASOA BRANCH | AE37: 130135 | AJ37: DZORWULU | AK37: 240122 | AM37: MANHYIA | AN37: 170605 | AS37: ABLENKPE | AT37: 40133 | AZ37: KNUST | BA37: 230604 | BC37: CAPE COAST | BD37: 50310 | BI37: AFFUL NKWANTA | BJ37: 180603 | BL37: AKONTOMBRA | BM37: 110405 | BO37: ASEMPANEYE | BP37: 90409 | BR37: HO | BS37: 190501 | CA37: FAMILY CARE FUNERAL TRUST | CB37: 100205 | CH37: Absa (GH) LTDDOME | CI37: 30170
C38: DARKUMAN | D38: 30173 | F38: TARKWA BRANCH | G38: 280401 | I38: KOFORIDUA | J38: 80221 | L38: SOUTH BIRIM RURAL BANK LTD-ACHIASE | M38: 70204 | X38: KNUST | Y38: 140604 | AA38: LABONE BRANCH | AB38: 340136 | AD38: KANTAMANTO BRANCH | AE38: 130136 | AJ38: MAMPROBI POSTBANK | AK38: 240123 | AM38: TAMALE BRANCH | AN38: 170801 | AS38: KASOA MAIN | AT38: 40134 | AZ38: FIRST ALLIED SAVINGS & LOANS LTD | BA38: 230651 | BC38: DUNKWA ON-OFFIN | BD38: 50327 | BI38: ABOABO | BJ38: 180604 | BL38: ESSAM | BM38: 110406 | BO38: ADABOKROM | BP38: 90410 | BR38: HARPER-KUMASI | BS38: 190601 | CA38: COMMERZ SAVINGS AND LOAN | CB38: 100206 | CH38: Absa (GH) LTDDARKUMAN | CI38: 30173
C39: INDEPENDENCE AVENUE | D39: 30175 | F39: TAKORADI BRANCH | G39: 280402 | I39: SUHUM | J39: 80222 | L39: UPPER MANYA KRO RURAL BANK LTD-ASESEWA | M39: 70205 | X39: ASAFO | Y39: 140605 | AA39: LAPAZ BRANCH | AB39: 340137 | AD39: MADINA CENTRAL BRANCH | AE39: 130137 | AJ39: KWAME NKRUMAH AVENUE | AK39: 240124 | AS39: SAFEBOUND (JUBILEE) TEMA | AT39: 40135 | AZ39: ST PETER'S CO-OPERATIVE CREDIT UNION | BA39: 230652 | BC39: SWEDRU BRANCH | BD39: 50337 | BI39: ATONSU | BJ39: 180605 | BL39: ASEMPANAYE | BM39: 110407 | BO39: TAKORADI MARKET CIRCLE | BP39: 90411 | BR39: SUAME | BS39: 190602 | CA39: NDK CAPITAL LIMITED | CB39: 100210 | CH39: Absa (GH) LTDINDEPENDENCE AVENUE | CI39: 30175
C40: WEIJA | D40: 30179 | F40: SEFWI BRANCH | G40: 280403 | I40: NKAWKAW | J40: 80223 | L40: KWAHU PRASO RURAL BANK LTD-KWAHU PRASO | M40: 70206 | X40: TAMALE | Y40: 140801 | AA40: MADINA MAIN BRANCH | AB40: 340138 | AD40: COMMUNITY1 BRANCH | AE40: 130138 | AJ40: ACHIMOTA BRANCH | AK40: 240125 | AS40: KISSEIMAN | AT40: 40136 | AZ40: NOBLE DREAM MICROFINANCE LTD | BA40: 230653 | BC40: KASOA | BD40: 50351 | BI40: SUAME MAAKRO | BJ40: 180606 | BL40: ADABOKROM | BM40: 110408 | BO40: HO | BP40: 90501 | BR40: ADUM | BS40: 190603 | CA40: GHANA STOCK EXCHANGE | CB40: 100211 | CH40: Absa (GH) LTDWEIJA | CI40: 30179
C41: ASHAIMAN | D41: 30184 | F41: ENCHI BRANCH | G41: 280404 | I41: ASIAKWA | J41: 80229 | L41: ATIWA RURAL BANK LTD-KWABENG | M41: 70207 | X41: UEW BRANCH | Y41: 310318 | AA41: MADINA NEW ROAD BRANCH | AB41: 340139 | AD41: SAKUMONO BRANCH | AE41: 130139 | AJ41: GWB LAPAZ | AK41: 240126 | AS41: SPINTEX ROAD | AT41: 40138 | AZ41: ADEHYEMAN SAVINGS & LOANS LTD | BA41: 230680 | BC41: TAKORADI | BD41: 50407 | BI41: SANTASI ROUNDABOUT BRANCH | BJ41: 180607 | BL41: ASANKRAGWA | BM41: 110409 | BO41: ADUM | BP41: 90601 | BR41: ASHTOWN | BS41: 190604 | CA41: DREAMSON GHANA LIMITED | CB41: 100212 | CH41: Absa (GH) LTDASHAIMAN | CI41: 30184
C42: HAATSO | D42: 30185 | F42: MARKET CIRCLE TAKORADI | G42: 280405 | I42: KADE | J42: 80230 | L42: MUMUADA RURAL BANK LTD-OSINO | M42: 70208 | X42: HO | Y42: 140501 | AA42: MALLAM JUNCTION BRANCH | AB42: 340140 | AD42: HIGH STREET BRANCH | AE42: 130140 | AJ42: NUNGUA | AK42: 240127 | AS42: ACCRA NORTH CIRCLE | AT42: 40139 | AZ42: TECHIMAN | BA42: 230701 | BC42: TARKWA BRANCH | BD42: 50434 | BI42: TECHIMAN | BJ42: 180701 | BL42: KUMASI | BM42: 110601 | BO42: KUMASI CENTRAL | BP42: 90602 | BR42: MULTI CREDIT SAVINGS AND LOANS - KUMASI | BS42: 190605 | CA42: ERISON CAPITAL LIMITED | CB42: 100213 | CH42: Absa (GH) LTDHAATSO | CI42: 30185
C43: KANESHIE | D43: 30187 | F43: HO BRANCH | G43: 280501 | I43: CAPE COAST | J43: 80331 | L43: AFRAM RURAL BANK LTD-TEASE | M43: 70209 | AA43: PIG FARM BRANCH | AB43: 340141 | AD43: KWASHIEMAN BRANCH | AE43: 130141 | AJ43: ASHAIMAN | AK43: 240128 | AS43: DANSOMAN | AT43: 40146 | AZ43: TAMALE | BA43: 230801 | BC43: FIRST GHANA BUILDING SOCIETY-TAKORADI | BD43: 50454 | BI43: TAMALE | BJ43: 180801 | BL43: ADUM | BM43: 110603 | BO43: BIBIANI | BP43: 90603 | BR43: KNUST | BS43: 190606 | CA43: SIC FINANCIAL SERVICES- MERCHANT BANK | CB43: 100214 | CH43: Absa (GH) LTDKANESHIE | CI43: 30187
C44: TEMA OIL REFINERY | D44: 30189 | F44: KUMASI ASAFO BRANCH | G44: 280601 | I44: ASSIN FOSO | J44: 80332 | L44: AKIM BOSOME RURAL BANK LTD-AKIM SWEDRU | M44: 70210 | AA44: MAMOBI BRANCH | AB44: 340142 | AD44: KISSEIMAN BRANCH | AE44: 130142 | AJ44: AIRPORT ACCRA | AK44: 240129 | AS44: ADENTA MARKET | AT44: 40147 | BC44: HO | BD44: 50503 | BL44: KUMASI MAGAZINE | BM44: 110604 | BO44: TEPA | BP44: 90604 | BR44: ASOKWA | BS44: 190607 | CA44: SIC BROKERAGE -MERCHANT BANK | CB44: 100215 | CH44: Absa (GH) LTDTEMA OIL REFINERY | CI44: 30189
C45: NORTH KANESHIE | D45: 30190 | F45: ADUM BRANCH | G45: 280602 | I45: UCC | J45: 80333 | L45: MPONUA RURAL BANK LTD-AMUANA PRASO | M45: 70211 | AA45: NIMA MAIN BRANCH | AB45: 340143 | AD45: ACCION | AE45: 130145 | AJ45: MAAMOBI | AK45: 240130 | AS45: NIMA BRANCH | AT45: 40148 | BC45: HOHOE BRANCH | BD45: 50535 | BL45: ASOKWA | BM45: 110605 | BO45: ASAFO | BP45: 90605 | BR45: SUNYANI | BS45: 190701 | CA45: GRADUATE ENTERPRISE CO-OPERATIVE CREDIT UNI | CB45: 100219 | CH45: Absa (GH) LTDNORTH KANESHIE | CI45: 30190
C46: MAAMOBI | D46: 30191 | F46: SUAME BRANCH | G46: 280603 | I46: MANKESSIM | J46: 80334 | L46: KWAEBIBIREM RURAL BANK LTD-ASUOM | M46: 70212 | AA46: MERIDIAN BRANCH | AB46: 340144 | AD46: OPPORTUNITY INT. SAVINGS AND LOAN | AE46: 130146 | AJ46: KOKOMLEMLE BRANCH | AK46: 240131 | AS46: NUNGUA | AT46: 40149 | BC46: NKWANTA BRANCH | BD46: 50541 | BL46: KNUST | BM46: 110613 | BO46: SUAME | BP46: 90606 | BR46: TAMALE | BS46: 190801 | CA46: JL PROPERTIES | CB46: 100220 | CH46: Absa (GH) LTDMAAMOBI | CI46: 30191
C47: OFFSHORE BANKING | D47: 30192 | F47: AMAKOM BRANCH | G47: 280604 | I47: TAKORADI | J47: 80441 | L47: AKYEM MANSA RURAL BANK LTD-AYIREBI | M47: 70213 | AA47: NORTH INDUSTRIAL AREA BRANCH | AB47: 340145 | AD47: EAST AIRPORT BRANCH | AE47: 130147 | AJ47: KANESHIE MAIN BRANCH | AK47: 240132 | AS47: ABEKA LAPAZ | AT47: 40150 | BC47: KUMASI | BD47: 50605 | BL47: TECHIMAN | BM47: 110710 | BO47: KEJETIA | BP47: 90607 | BR47: BOLGATANGA | BS47: 190901 | CA47: DUSK CAPITAL LIMITED | CB47: 100221 | CH47: Absa (GH) LTDOFFSHORE BANKING | CI47: 30192
C48: MATAHEKO | D48: 30193 | F48: ALABAR KUMASI | G48: 280605 | I48: ENCHI | J48: 80444 | L48: SOUTH AKIM RURAL BANK LTD-NANKESE | M48: 70214 | AA48: CASTLE ROAD BRANCH | AB48: 340146 | AD48: KWABENYA BRANCH | AE48: 130148 | AJ48: TEMA COMM. 1 MAIN BRANCH | AK48: 240133 | AS48: HAATSO | AT48: 40162 | BC48: KUMASI CENTRAL | BD48: 50619 | BL48: GOASO | BM48: 110711 | BO48: SUNYANI | BP48: 90701 | BR48: WA | BS48: 191001 | CA48: LESFAM COMPANY LIMITED | CB48: 100222 | CH48: Absa (GH) LTDMATAHEKO | CI48: 30193
C49: ADENTA | D49: 30194 | F49: KNUST KUMASI | G49: 280606 | I49: TAKORADI HARBOUR | J49: 80445 | L49: ODWEN-ANOMA RURAL BANK LTD-KWEEHWEE | M49: 70215 | AA49: OXFORD STREET BRANCH | AB49: 340147 | AD49: OKPONGLO BRANCH | AE49: 130149 | AJ49: MADINA MARKET BRANCH | AK49: 240134 | AS49: AMASAMAN | AT49: 40163 | BC49: OBUASI | BD49: 50621 | BL49: TAMALE | BM49: 110814 | BO49: BEREKUM | BP49: 90741 | BR49: WA COOPERATIVE CREDIT UNION LTD - WA BRANCH | BS49: 191002 | CA49: ALLIANZ LIFE INSURANCE CO. LTD | CB49: 100224 | CH49: Absa (GH) LTDADENTA | CI49: 30194
C50: ABOSSEY OKAI | D50: 30195 | F50: KEJETIA KUMASI | G50: 280607 | I50: AGONA NKWANTA | J50: 80446 | L50: DUMPONG RURAL BANK LTD-OFRAMASE | M50: 70216 | AA50: POKUASE BRANCH | AB50: 340148 | AD50: ASHAIMAN | AE50: 130150 | AJ50: TUDU MAIN | AK50: 240135 | AS50: ADJIRIGANO | AT50: 40164 | BC50: ASOKWA BRANCH | BD50: 50632 | BL50: BOLGA | BM50: 110901 | BO50: TAMALE | BP50: 90801 | CA50: FARMER WORLD GH. LTD | CB50: 100227 | CH50: Absa (GH) LTDABOSSEY OKAI | CI50: 30195
C51: KOTOBABI | D51: 30196 | F51: MULTICREDIT SAVINGS AND LOANS COMPANY | G51: 280696 | I51: GREL | J51: 80447 | L51: ADONTEN COMMUNITY BANK LTD-NEW TAFO | M51: 70217 | AA51: ABBOSEY OKAI BRANCH | AB51: 340149 | AD51: KWAME NKRUMAH AVENUE BRANCH | AE51: 130153 | AJ51: DANSOMAN MAIN | AK51: 240136 | AS51: WEIJA BRANCH | AT51: 40165 | BC51: ASHANTI MAMPONG BRANCH | BD51: 50643 | BO51: BOLGATANGA | BP51: 90901 | CA51: EXPERTRAVELS & TOURS LTD | CB51: 100228 | CH51: Absa (GH) LTDKOTOBABI | CI51: 30196
C52: PALM WINE JUNCTION | D52: 30197 | F52: TECHIMAN BRANCH | G52: 280701 | I52: ADB-JUABOSO | J52: 80448 | L52: FANTEAKWA RURAL BANK LTD-KOFORIDUA | M52: 70218 | AA52: SHIPPERS HOUSE BRANCH | AB52: 340150 | AD52: ADEHYEMAN SAVINGS & LOAN | AE52: 130154 | AJ52: ABEKA | AK52: 240138 | AS52: KATAMANTO | AT52: 40166 | BC52: SUAME BRANCH | BD52: 50645 | BO52: WA | BP52: 91001 | CA52: HARIMART DIRECT | CB52: 100229 | CH52: Absa (GH) LTDPALM WINE JUNCTION | CI52: 30197
C53: KOFORIDUA | D53: 30242 | F53: TAMALE BRANCH | G53: 280801 | I53: HO | J53: 80552 | L53: SUHUM RURAL BANK | M53: 70219 | AA53: SAKUMONO BRANCH | AB53: 340151 | AD53: GN SAVINGS & LOANS LTD | AE53: 130155 | AJ53: ASHAIMAN MARKET | AK53: 240142 | AS53: ADABRAKA | AT53: 40167 | BC53: KUMASI CITY MALL | BD53: 50648 | CA53: KASOA | CB53: 100501 | CH53: Absa (GH) LTDKOFORIDUA | CI53: 30242
C54: NKAWKAW | D54: 30243 | F54: BOLGATANGA | G54: 280901 | I54: KPANDO | J54: 80553 | L54: EAST AKIM RURAL BANK LIMITED | M54: 70220 | AA54: SOUTH LEGON BRANCH | AB54: 340152 | AD54: UNION SAVINGS & LOANS | AE54: 130158 | AJ54: AIRPORT PC | AK54: 240143 | AS54: AIRPORT CITY | AT54: 40168 | BC54: TANOSO | BD54: 50650 | CA54: ASAFO | CB54: 100603 | CH54: Absa (GH) LTDNKAWKAW | CI54: 30243
C55: ODA | D55: 30246 | F55: WA UPPER WEST | G55: 281001 | I55: NKWANTA | J55: 80554 | L55: CAPE COASTCAPE COAST | M55: 70301 | AA55: EAST AIRPORT BRANCH | AB55: 340153 | AD55: BEIGE CAPITAL | AE55: 130160 | AJ55: KASOA | AK55: 240144 | AS55: EAST LEGON | AT55: 40169 | BC55: FIRST GHANA BUILDING SOCIETY- KUMASI SUAME | BD55: 50655 | CA55: BANTAMA | CB55: 100604 | CH55: Absa (GH) LTDODA | CI55: 30246
C56: NSAWAM | D56: 30247 | I56: DENU | J56: 80555 | L56: ENYAN DENKYIRA RURAL BANK LTD-ENYAN DENKYIRA | M56: 70302 | AA56: BAATSONA BRANCH | AB56: 340154 | AD56: NBFI-ADVANS GH | AE56: 130161 | AJ56: DOME | AK56: 240145 | AS56: TEMA COMMUNITY 2 | AT56: 40170 | BC56: FIRST GHANA BUILDING SOCIETY- KUMASI AMAKOM | BD56: 50658 | CA56: ADUM | CB56: 100605 | CH56: Absa (GH) LTDNSAWAM | CI56: 30247
C57: SOMANYA BRANCH | D57: 30286 | I57: JUAPONG | J57: 80556 | L57: KAKUM RURAL BANK LTD-ELMINA | M57: 70303 | AA57: OPERA SQUARE BRANCH | AB57: 340155 | AD57: NEW ABEKA | AE57: 130162 | AJ57: KANESHIE MARKET | AK57: 240146 | AS57: OKAISHIE | AT57: 40171 | BC57: SUNYANI | BD57: 50706 | CA57: KONONGO | CB57: 100606 | CH57: Absa (GH) LTDSOMANYA BRANCH | CI57: 30286
C58: SWEDRU BRANCH | D58: 30320 | I58: SOGAKOPE | J58: 80557 | L58: NYANKUMASE AHENKRO RURAL BANK LTD-FANTI NYANKUMASE | M58: 70304 | AA58: TEMA COMMUNITY 2 BRANCH | AB58: 340156 | AD58: GOLDEN PRIDE S&L | AE58: 130163 | AJ58: MADINA | AK58: 240147 | AS58: CENTRAL UNIVERSITY COLLEGE | AT58: 40172 | BC58: TECHIMAN | BD58: 50715 | CA58: TECHIMAN | CB58: 100701 | CH58: Absa (GH) LTDSWEDRU BRANCH | CI58: 30320
C59: CAPE COAST | D59: 30337 | I59: KPEVE | J59: 80558 | L59: ASSINMAN RURAL BANK LTD-ASSIN MANSO | M59: 70305 | AA59: TEMA COMMUNITY 25 BRANCH | AB59: 340157 | AD59: PRIVATE BANKING | AE59: 130164 | AJ59: OSU DANQUAH CIRCLE | AK59: 240148 | AS59: LABONE | AT59: 40173 | BC59: WENCHI | BD59: 50725 | CA59: TAMALE | CB59: 100801 | CH59: Absa (GH) LTDCAPE COAST | CI59: 30337
C60: OBUASI | D60: 30338 | I60: KPASSA | J60: 80559 | L60: AKATAKYIMAN RURAL BANK LTD-KOMENDA | M60: 70306 | AA60: TESANO BRANCH | AB60: 340158 | AD60: NBFI-LEGACY CAPITAL S&L | AE60: 130166 | AJ60: NUNGUA BRIGADE | AK60: 240149 | AS60: ACHIMOTA | AT60: 40174 | BC60: KINTAMPO | BD60: 50726 | CH60: Absa (GH) LTDOBUASI | CI60: 30338
C61: WINNEBA | D61: 30365 | I61: KUMASI ADUM | J61: 80661 | L61: EKUMFIMAN RURAL BANK LTD-ESSUEHYIA | M61: 70307 | AA61: TESHIE BRANCH | AB61: 340159 | AD61: NBFI-DIRECT SAVINGS AND LOANS | AE61: 130167 | AJ61: TEMA COMMUNITY 25 | AK61: 240150 | AS61: A&C MALL | AT61: 40175 | BC61: NTOROSO | BD61: 50730 | CH61: Absa (GH) LTDWINNEBA | CI61: 30365
C62: MANKESSIM | D62: 30367 | I62: BKWAI | J62: 80662 | L62: AKOTI RURAL BANK LTD-ASSIN AKROPONG | M62: 70308 | AA62: TRADE FAIR BRANCH | AB62: 340160 | AD62: NBFI-QUEEN OF PEACE CO-OPERATIVE U | AE62: 130168 | AJ62: WIEJA | AK62: 240151 | AS62: TESANO | AT62: 40176 | BC62: FIRST GHANA BUILDING SOCIETY- SUNYANI | BD62: 50756 | CH62: Absa (GH) LTDMANKESSIM | CI62: 30367
C63: TWIFO PRASO | D63: 30399 | I63: NEW EDUBIASE | J63: 80663 | L63: TWIFO RURAL BANK LTD-TWIFO AGONA | M63: 70309 | AA63: ABEKA BRANCH | AB63: 340161 | AD63: NEW ABIREM | AE63: 130201 | AJ63: FIDELITY - EAST LEGON | AK63: 240152 | AS63: ABOSSEY OKAI | AT63: 40177 | BC63: TAMALE | BD63: 50808 | CH63: Absa (GH) LTDTWIFO PRASO | CI63: 30399
C64: HIGH STREET-TAKORADI | D64: 30431 | I64: OBUASI | J64: 80664 | L64: MFANTSIMAN COMMUNITY RURAL BANK LTD-BIRIWA | M64: 70310 | AA64: UG BRANCH | AB64: 340162 | AD64: TAKORADI | AE64: 130401 | AJ64: HOHOE | AK64: 240191 | AS64: MANDELA PARK | AT64: 40178 | BC64: SAWLA BRANCH | BD64: 50840 | CH64: Absa (GH) LTDHIGH STREET-TAKORADI | CI64: 30431
C65: LIBERATION ROAD-TAKORADI | D65: 30432 | I65: ADB-KUMASI CENTRAL MARKET | J65: 80665 | L65: TAKORADI CENTRE-TAKORADI | M65: 70401 | AA65: WEIJA BRANCH | AB65: 340163 | AD65: TARKWA | AE65: 130402 | AJ65: NKWAKAW BRANCH | AK65: 240201 | AS65: OSU OXFORD STREET | AT65: 40179 | BC65: UDS TAMALE BRANCH | BD65: 50842 | CH65: Absa (GH) LTDLIBERATION ROAD-TAKORADI | CI65: 30432
C66: TARKWA | D66: 30434 | I66: KUMASI ASOKWA | J66: 80666 | L66: ANKOBRA WEST (ESIAMA) RURAL BANK LTD-ESIAMA | M66: 70402 | AA66: WISCONSIN BRANCH | AB66: 340164 | AD66: TAKORADI MARKET CIRCLE | AE66: 130403 | AJ66: ASSIN FOSU | AK66: 240301 | AS66: MARTEY TSURU | AT66: 40180 | BC66: YENDI | BD66: 50844 | CH66: Absa (GH) LTDTARKWA | CI66: 30434
C67: TARKWA MINES | D67: 30451 | I67: ADB-KUMASI PREMPEH 11 STREET | J67: 80667 | L67: AMENFIMAN RURAL BANK LTD-WASSA AKROPONG | M67: 70403 | AA67: ZENU BRANCH | AB67: 340165 | AD67: ELUBU | AE67: 130404 | AJ67: CAPE COAST | AK67: 240302 | AS67: TEMA COMMUNITY 1 | AT67: 40181 | BC67: FIRST GHANA BUILDING SOCIETY- TAKORADI | BD67: 50857 | CH67: Absa (GH) LTDTARKWA MINES | CI67: 30451
C68: ASANKRAGUA | D68: 30452 | I68: AMAKOM | J68: 80668 | L68: NZEMA MANLE RURAL BANK LTD-AWIEBO | M68: 70404 | AA68: GOLDEN LINK SAVINGS AND LOANS LIMITED | AB68: 340191 | AD68: TAKORADI COLLINS STREET | AE68: 130405 | AJ68: TAKORADI MARKET CIRCLE | AK68: 240401 | AS68: MADINA ZONGO JUNCTION | AT68: 40182 | BC68: BOLGATANGA | BD68: 50902 | CH68: Absa (GH) LTDASANKRAGUA | CI68: 30452
C69: TAKORADI KOKOMPE | D69: 30456 | I69: SEFWI WIAWSO | J69: 80684 | L69: JOMORO RURAL BANK LTD-TIKOBO NO. 1 | M69: 70405 | AA69: PROGRESS SAVINGS AND LOANS | AB69: 340197 | AD69: ESIAMA BRANCH | AE69: 130406 | AJ69: TARKWA | AK69: 240402 | AS69: DZORWULU BRANCH | AT69: 40183 | BC69: WA | BD69: 51014 | CH69: Absa (GH) LTDTAKORADI KOKOMPE | CI69: 30456
C70: ELUBO | D70: 30498 | I70: ATEBUBU | J70: 80685 | L70: LOWER PRA RURAL BANK LTD-SHAMA | M70: 70406 | AA70: BEST POINT SAVINGS AND LOAN | AB70: 340198 | AD70: AFLAO | AE70: 130501 | AJ70: TAKORADI POSTBANK | AK70: 240403 | AS70: AIRPORT TERMINAL 3 | AT70: 40184 | BC70: FIRST GHANA BUILDING SOCIETY-HOHOE | BD70: 51153 | CH70: Absa (GH) LTDELUBO | CI70: 30498
C71: HO | D71: 30539 | I71: BONSO NKWANTA | J71: 80686 | L71: FIASEMAN (BOGOSO AREA) RURAL BANK LTD-BOGOSO | M71: 70407 | AA71: UNICREDIT SAVINGS AND LOANS | AB71: 340199 | AD71: KUMASI HARPER ROAD | AE71: 130601 | AJ71: TARKWA MAIN | AK71: 240405 | AS71: HEAD OFFICE | AT71: 40199 | CH71: Absa (GH) LTDHO | CI71: 30539
C72: HOHOE | D72: 30540 | I72: SEFWI ESSAM | J72: 80687 | L72: MANSOMAN RURAL BANK LTD-MANSO-AMENFI | M72: 70408 | AA72: ABETIFI BRANCH | AB72: 340201 | AD72: JUBILEE HOUSE | AE72: 130602 | AJ72: TAKORADI EFFIEKUMA | AK72: 240406 | AS72: KOFORIDUA | AT72: 40201 | CH72: Absa (GH) LTDHOHOE | CI72: 30540
C73: AFLAO | D73: 30572 | I73: SUNYANI | J73: 80771 | L73: AHANTAMAN RURAL BANK LTD-AGONA NKWANTA | M73: 70409 | AA73: KOFORIDUA BRANCH | AB73: 340202 | AD73: KNUST | AE73: 130603 | AJ73: TAKORADI MAIN | AK73: 240407 | AS73: AKIM ODA | AT73: 40202 | CH73: Absa (GH) LTDAFLAO | CI73: 30572
C74: ASAFO | D74: 30623 | I74: DORMAA AHENKRO | J74: 80772 | L74: WESTERN RURAL BANK LTD-WASSA AKROPONG | M74: 70410 | AA74: MAMFE BRANCH | AB74: 340203 | AD74: ADUM | AE74: 130604 | AJ74: HO | AK74: 240501 | AS74: KADE | AT74: 40203 | CH74: Absa (GH) LTDASAFO | CI74: 30623
C75: PREMPEH II STREET | D75: 30627 | I75: BEREKUM | J75: 80774 | L75: HO CENTRE-HO | M75: 70501 | AA75: NEW ABIREM BRANCH | AB75: 340204 | AD75: ABREPO JUNCTION | AE75: 130605 | AJ75: STADIUM POST | AK75: 240601 | AS75: NEW TAFO | AT75: 40205 | CH75: Absa (GH) LTDPREMPEH II STREET | CI75: 30627
C76: KEJETIA- KUMASI | D76: 30628 | I76: NKORANSAH | J76: 80775 | L76: NORTH TONGU RURAL BANK LTD-ADIDOME | M76: 70502 | AA76: UCC BRANCH | AB76: 340301 | AD76: TAFO | AE76: 130606 | AJ76: KUMASI-ADUM | AK76: 240602 | AS76: NKAWKAW | AT76: 40206 | CH76: Absa (GH) LTDKEJETIA- KUMASI | CI76: 30628
C77: NEW SUAME MAGAZINE | D77: 30653 | I77: TECHIMAN | J77: 80776 | L77: AVENOR RURAL BANK LTD-AKATSI | M77: 70503 | AA77: DUNKWA ON OFFIN BRANCH | AB77: 340302 | AD77: ASH TOWN | AE77: 130607 | AJ77: KUMASI-SUAME | AK77: 240603 | AS77: SOMANYA | AT77: 40207 | CH77: Absa (GH) LTDNEW SUAME MAGAZINE | CI77: 30653
C78: OLD SUAME MAGAZINE | D78: 30657 | I78: GOASO | J78: 80777 | L78: UNITY RURAL BANK LTD-ZIOPE | M78: 70504 | AA78: SWEDRU BRANCH | AB78: 340303 | AD78: KEJETIA | AE78: 130608 | AJ78: ATONSU | AK78: 240604 | AS78: ASAMANKESE | AT78: 40208 | CH78: Absa (GH) LTDOLD SUAME MAGAZINE | CI78: 30657
C79: AGOGO | D79: 30658 | I79: KWAPONG | J79: 80778 | L79: WETO RURAL BANK LTD-KPEVE | M79: 70505 | AA79: WINNEBA BRANCH | AB79: 340304 | AD79: ABREPO MAIN | AE79: 130609 | AJ79: AHODWO | AK79: 240605 | AS79: AKROPONGAKWAPIM | AT79: 40209 | CH79: Absa (GH) LTDAGOGO | CI79: 30658
C80: ADUM | D80: 30666 | I80: KENYASE | J80: 80779 | L80: BUTAWU RURAL BANK LTD-HO | M80: 70506 | AA80: ASAWINSO | AB80: 340401 | AD80: BANTAMA | AE80: 130610 | AJ80: KUMASI ADUM POSTBANK | AK80: 240606 | AS80: MAMPONGAKWAPIM | AT80: 40210 | CH80: Absa (GH) LTDADUM | CI80: 30666
C81: BANTAMA | D81: 30674 | I81: TAMALE | J81: 80881 | L81: KUMASIKUMASI | M81: 70601 | AA81: AXIM ROAD BRANCH | AB81: 340402 | AD81: STADIUM | AE81: 130611 | AJ81: KO METHODIST | AK81: 240607 | AS81: ANYIMAN | AT81: 40212 | CH81: Absa (GH) LTDBANTAMA | CI81: 30674
C82: SEFWI-WIASO | D82: 30676 | I82: TAMALE ABOABO | J82: 80882 | L82: ATWIMA RURAL BANK LTD-FOASE | M82: 70602 | AA82: MARKET CIRCLE | AB82: 340403 | AD82: TANOSO | AE82: 130612 | AJ82: SANTASI ROUNDABOUT | AK82: 240608 | AS82: ADA FOAH | AT82: 40213 | CH82: Absa (GH) LTDSEFWI-WIASO | CI82: 30676
... C91: GOASO | D91: 30759 | I91: TUMU | J91: 80994 | L91: BOSOMTWI RURAL BANK LTD-KUNTANASE | M91: 70611 | AA91: ASOKWA BRANCH | AB91: 340607 | AD91: HEAD OFFICE OPERATION | AE91: 130998 | AJ91: SUNYANI | AK91: 240704 | AS91: KOFORIDUA CENTRAL GCB BANK LIMITED | AT91: 40224 | CH91: Absa (GH) LTDGOASO | CI91: 30759
C92: ATEBUBU | D92: 30778 | I92: WA | J92: 80995 | L92: OKOMFO ANOKYE RURAL BANK LTD-WIAMOASE | M92: 70612 | AA92: ATONSU BRANCH | AB92: 340608 | AJ92: TAMALE | AK92: 240801 | AS92: KOFORIDUA CENTRAL | AT92: 40244 | CH92: Absa (GH) LTDATEBUBU | CI92: 30778
C93: TAMALE | D93: 30833 | I93: WALEWALE | J93: 80996 | L93: DENKYIRAMAN RURAL BANK LTD-AYAMFURI | M93: 70613 | AA93: BANTAMA BRANCH | AB93: 340609 | AJ93: BOLGATANGA POSTBANK | AK93: 240901 | AS93: CAPE COAST MAIN | AT93: 40301 | CH93: Absa (GH) LTDTAMALE | CI93: 30833
C94: GUMANI | D94: 30871 | I94: HOHOE | J94: 81151 | L94: ASAWINSO RURAL BANK LTD-SEFWI-ASAWINSO | M94: 70614 | AA94: EJISU BRANCH | AB94: 340610 | AJ94: WA | AK94: 241090 | AS94: UNIVERSITY OF CAPE COAST | AT94: 40302 | CH94: Absa (GH) LTDGUMANI | CI94: 30871
C95: BOLGATANGA | D95: 30919 | L95: ODOTOBRI RURAL BANK LTD-JACOBU | M95: 70615 | AA95: HARPER ROAD BRANCH | AB95: 340611 | AS95: AGONA SWEDRU | AT95: 40303 | CH95: Absa (GH) LTDBOLGATANGA | CI95: 30919
C96: BAWKU | D96: 30926 | L96: ATWIMA KWANWOMA RURAL BANK LTD-PAKYI NO. 2 | M96: 70616 | AA96: KEJETIA BRANCH | AB96: 340612 | AS96: ASSIN FOSU | AT96: 40304 | CH96: Absa (GH) LTDBAWKU | CI96: 30926
C97: WA | D97: 31088 | L97: SEKYERE RURAL BANK LTD-JAMASI | M97: 70618 | AA97: KNUST BRANCH | AB97: 340613 | AS97: WINNEBA | AT97: 40305 | CH97: Absa (GH) LTDWA | CI97: 31088
L98: AMANANO RURAL BANK LTD-NYINAHIM | M98: 70619 | AA98: NYHIAESO BRANCH | AB98: 340614 | AS98: BREMAN ASIKUMA | AT98: 40306 | CH98: Access Bank (Ghana) PlcHEAD OFFICE | CI98: 280100
L99: AMASIE WEST RURAL BANK LTD-ANTOAKROM | M99: 70620 | AA99: ROMAN HILL BRANCH | AB99: 340615 | AS99: ABURA DUNKWA | AT99: 40307 | CH99: Access Bank (Ghana) PlcEAST CANTONMENTS BRANCH | CI99: 280101
L100: JUABEN RURAL BANK LTD-JUABEN | M100: 70621 | AA100: SOKOBAN BRANCH | AB100: 340616 | AS100: SALTPOND | AT100: 40308 | CH100: Access Bank (Ghana) PlcTEMA MAIN BRANCH | CI100: 280102
L101: YAPRA RURAL BANK LTD-PRANG | M101: 70622 | AA101: ASHTOWN BRANCH | AB101: 340617 | AS101: MANKESSIM | AT101: 40309 | CH101: Access Bank (Ghana) PlcOSU OXFORD BRANCH | CI101: 280103
L102: NWABIAGYA RURAL BANK LTD-BAREKESE | M102: 70623 | AA102: SUAME BRANCH | AB102: 340618 | AS102: TWIFO PRASO | AT102: 40310 | CH102: Access Bank (Ghana) PlcLASHIBI BRANCH | CI102: 280104
L103: ATWIMA MPONUA RURAL BANK LTD-TOASE | M103: 70624 | AA103: TAFO BRANCH | AB103: 340619 | AS103: ELMINA | AT103: 40315 | CH103: Access Bank (Ghana) PlcOSU WATSON BRANCH | CI103: 280105
L104: OTUASEKAN RURAL BANK LTD-KOFIASE | M104: 70625 | AA104: ROMAN HILL MARKET BRANCH | AB104: 340620 | AS104: CORONATION JUNCTION | AT104: 40317 | CH104: Access Bank (Ghana) PlcKANTAMANTO BRANCH | CI104: 280106
L105: UPPER AMENFI RURAL BANK LTD-ANKWAWSO | M105: 70626 | AA105: KRONUM BRANCH | AB105: 340621 | AS105: TAKORADI MAIN | AT105: 40401 | CH105: Access Bank (Ghana) PlcKANESHIE BRANCH | CI105: 280107
L106: BIA-TORYA RURAL BANK LTD-BONSU-NKWANTA | M106: 70627 | AA106: ABUAKWA BRANCH | AB106: 340622 | AS106: TAKORADI HARBOUR | AT106: 40402 | CH106: Access Bank (Ghana) PlcCASTLE ROAD BRANCH | CI106: 280108
L107: AMATIN AND KASEI COMMUNITY BANK LTD-KASEI | M107: 70628 | AA107: SUNYANI MAIN BRANCH | AB107: 340701 | AS107: TAKORADI MARKET CIRCLE | AT107: 40403 | CH107: Access Bank (Ghana) PlcACCESS BANK -MADINA BRANCH | CI107: 280109
L108: NSUTAMAN RURAL BANK LTD-NSUTA | M108: 70629 | AA108: SUNYANI POST OFFICE BRANCH | AB108: 340702 | AS108: SEKONDI | AT108: 40404 | CH108: Access Bank (Ghana) PlcSOUTH INDUSTRIAL BRANCH | CI108: 280110
L109: SEFWIMAN RURAL BANK LTD-SEFWI-ASAW | M109: 70630 | AA109: TECHIMAN MARKET BRANCH | AB109: 340703 | AS109: TARKWA | AT109: 40405 | CH109: Access Bank (Ghana) PlcNIA BRANCH | CI109: 280111
...

Sheet Helper Data
A1: MALE | B1: SINGLE | C1: FULL TIME | D1: YES | E1: SALARY | F1: BANK | G1: MTN | H1: Access Bank (Ghana) Plc | I1: TITLES | J1: WORKER TYPES | K1: Currency | L1: National ID Types | M1: Countries (Nationalities)
A2: FEMALE | B2: MARRIED | C2: PART TIME | D2: NO | E2: WAGE | F2: MOMO | G2: VODAFONE | H2: Agricultural Development Bank Limited | I2: Mr | J2: EMPLOYEE | K2: GHS | L2: Ghana Card | M2: Afghanistan
B3: WIDOWED | C3: CONTRACT | F3: CASH | G3: AIRTELTIGO | H3: Apex Bank GH Limited | I3: Miss | J3: CONTRACTOR | K3: USD | L3: Drivers License | M3: Albania
C4: PROBATION | F4: CHEQUE | H4: Bank of Africa Ghana Limited | I4: Mrs | K4: EUR | L4: NHIS Card | M4: Algeria
H5: Absa (GH) LTD | I5: Ms | K5: GBP | L5: Voters ID Card | M5: American Samoa
H6: CAL Bank Limited | I6: Sir | K6: CNY | L6: Passport | M6: Andorra
H7: Consolidated Bank Ghana Limited | I7: Dr | K7: ZAR | L7: Other | M7: Angola
H8: Ecobank Ghana Limited | I8: Chancellor | M8: Anguilla
H9: FBNBank (Ghana) Limited | I9: Vice-Chancellor | M9: Antigua & Barbuda
H10: Fidelity Bank Limited | I10: Excellency | M10: Argentina
H11: First Atlantic Bank Limited | I11: Professor | M11: Armenia
H12: First National Bank (Ghana) Limited | M12: Aruba
H13: GCB Bank Limited | M13: Australia
H14: GHL Bank Limited | M14: Austria
H15: Guaranty Trust Bank (Ghana) Limited | M15: Azerbaijan
H16: National Investment Bank Limited | M16: Bahamas, The
H17: Omni-BSIC Bank Ghana Limited | M17: Bahrain
H18: Prudential Bank Limited | M18: Bangladesh
H19: Republic Bank (Ghana) Limited | M19: Barbados
H20: Societe General (Ghana) Limited | M20: Belarus
H21: Stanbic Bank Ghana Limited | M21: Belgium
H22: Standard Chartered Bank (Ghana) Limited | M22: Belize
H23: United Bank for Africa (Ghana) Limited | M23: Benin
... H26: Other | M26: Bolivia
M27: Bosnia & Herzegovina
M28: Botswana
M29: Brazil
M30: British Virgin Is.
M31: Brunei
M32: Bulgaria
M33: Burkina Faso
M34: Burma
M35: Burundi
M36: Cambodia
M37: Cameroon
M38: Canada
... M228: Zimbabwe
